Workbook

Sheet Start Here
A1: hona
A8: THE FIX & FLIP WORKBOOK
B11: Run a flip without having run one before.
B12: Answer the questions on Your Deal. Put six sold houses on Comps. Untick what this house does not need on Scope & Phases. Send the Bid Request to subs and type back what they quote. Everything else fills itself in.
A15: WHERE YOU ARE
B17: Step | C17: What it is | D17: Done
B18: 1. Your Deal | C18: Fourteen questions about the house, the money and your terms. | D18: =COUNTA('Your Deal'!$D$6:$D$40) -> 14 | E18: 14
B19: 2. Comps & Buy Box | C19: Three sold as-is, three sold renovated. Gives you your ceiling. | D19: =COUNT('Comps & Buy Box'!$C$8:$C$10)+COUNT('Comps & Buy Box'!$C$16:$C$18) -> 6 | E19: 6
B20: 3. Scope & Phases | C20: Untick anything this house does not need. | D20: =COUNTIF('Scope & Phases'!$D$8:$D$73,"x") -> 52 | E20: jobs
B21: 4. Bid Comparison | C21: What each sub quoted — price and days. | D21: =COUNTIF('Bid Comparison'!$N$8:$N$73,">0") -> 52 | E21: priced
A23: WHAT IT TELLS YOU
B25: Most you should pay | D25: ='Comps & Buy Box'!$D$33 -> 276826.14
B26: Rehab budget from your bids | D26: ='Budget & Schedule'!$D$5 -> 129325
B27: Cost per square foot | D27: ='Budget & Schedule'!$D$6 -> 69.52957
B28: Days on site | D28: ='Budget & Schedule'!$D$7 -> 155
B29: Extra cash you need between draws | D29: ='Cash & Float'!$F$21 -> 0
B32: Blue cells are yours to fill in. Grey cells calculate themselves — leave them alone.
B34: Need help? Email support@honafinancial.com with any question about this workbook.
B36: When the numbers are right, the last sheet hands your project straight to Hona — and every receipt you scan lands against them. honafinancial.com

Sheet Your Deal
A1: Your Deal
A2: Answer these in order. Everything else in this workbook fills itself in.
A5: THE PROPERTY
A7: 1. Property address | D7: 1421 E Cloud Rd, Queen Creek AZ
A8: Street, city, state
A9: 2. Square footage | D9: 1860
A10: Heated and cooled area only
A11: 3. What are you paying for it? | D11: 255000
A12: Purchase price. Leave blank if you have not offered yet.
A13: 4. How rough is it? | D13: Medium
A14: Light / Medium / Heavy / Rebuild — this pre-ticks your scope
A16: THE MONEY
A18: 5. How much are you borrowing? | D18: 310000
A19: Total loan amount including rehab draws
A20: 6. Interest rate | D20: 0.115
A21: Annual rate, e.g. 11.5%
A22: 7. Points | D22: 2
A23: Origination points charged at closing
A24: 8. Days from draw request until your lender funds | D24: 10
A25: Ask them. This drives how much cash you carry.
A26: 9. How much of your own cash can you put in? | D26: 60000
A27: Cash available for deposits and carry, not the down payment
A29: YOUR TERMS
A31: 10. When do you start? | D31: 46314
A32: First day of work on site
A33: 11. What do subs get up front? | D33: 0.5
A34: Arizona residential standard is 50% down, 50% on completion
A35: 12. Does your lender hold back a retainage? | D35: 0.1
A36: Percentage held from each draw until completion
A37: 13. Selling costs when you exit | D37: 0.08
A38: Agent commission plus closing. 8% is a common default.
A39: 14. What profit are you aiming for? | D39: 55000
A40: Your number, not a formula. This sets your maximum offer.
A43: Everything above is filled in with an example deal so you can see how it works. Replace it with yours.
A44: Need help? Email support@honafinancial.com with any question about this workbook.

Sheet Comps & Buy Box
A1: Comps & Buy Box
A2: Six sales tell you what this house is worth now, what it is worth finished, and the most you should pay.
A5: AS-IS COMPARABLES — WHAT HOUSES LIKE THIS SELL FOR BEFORE ANYONE TOUCHES THEM
A7: Address | B7: Sq ft | C7: Sold price | D7: $ / sq ft | E7: Notes
A8: 1188 E Silver Creek Rd | B8: 1795 | C8: 262000 | D8: =IFERROR(C8/B8,"") -> 145.961 | E8: Sold as-is, dated kitchen
A9: 22410 S 213th St | B9: 1902 | C9: 271000 | D9: =IFERROR(C9/B9,"") -> 142.4816 | E9: Estate sale, original baths
A10: 1640 W Kingman Loop | B10: 1748 | C10: 249000 | D10: =IFERROR(C10/B10,"") -> 142.44851 | E10: Investor purchase, roof issue
C11: Average $ / sq ft | D11: =IFERROR(AVERAGE(D8:D10),0) -> 143.63037
A13: FINISHED COMPARABLES — WHAT HOUSES LIKE THIS SELL FOR RENOVATED (YOUR ARV)
A15: Address | B15: Sq ft | C15: Sold price | D15: $ / sq ft | E15: Notes
A16: 1355 E Cloud Rd | B16: 1880 | C16: 529000 | D16: =IFERROR(C16/B16,"") -> 281.38298 | E16: Full reno, quartz + LVP
A17: 22188 S 214th Way | B17: 1815 | C17: 512000 | D17: =IFERROR(C17/B17,"") -> 282.09366 | E17: Updated 2025, new HVAC
A18: 1502 W Kingman Loop | B18: 1930 | C18: 545000 | D18: =IFERROR(C18/B18,"") -> 282.38342 | E18: Reno + pool resurface
C19: Average $ / sq ft | D19: =IFERROR(AVERAGE(D16:D18),0) -> 281.95335
A21: THE BUY BOX — THE MOST YOU SHOULD PAY FOR THIS HOUSE
A23: Walk a neighborhood, type a square footage above, and this tells you your ceiling before you make an offer.
A25: Estimated as-is value | D25: ='Your Deal'!$D$9*'Comps & Buy Box'!$D$11 -> 267152.49
A26: Estimated ARV (finished value) | D26: ='Your Deal'!$D$9*'Comps & Buy Box'!$D$19 -> 524433.24
A28: Less selling costs | D28: =-$D$26*'Your Deal'!$D$37 -> -41954.659
A29: Less rehab budget | D29: =-'Budget & Schedule'!$D$5 -> -129325
A30: Less loan carry and points | D30: =-(('Your Deal'!$D$18*'Your Deal'!$D$20)*('Budget & Schedule'!$D$8/12)+'Your Deal'!$D$18*('Your Deal'!$D$22/100)) -> -21327.436
A31: Less your target profit | D31: =-'Your Deal'!$D$39 -> -55000
A33: MAXIMUM YOU SHOULD PAY | D33: =$D$26-$D$26*'Your Deal'!$D$37-'Budget & Schedule'!$D$5-(('Your Deal'!$D$18*'Your Deal'!$D$20)*('Budget & Schedule'!$D$8/12)+'Your Deal'!$D$18*('Your Deal'!$D$22/100))-'Your Deal'!$D$39 -> 276826.14
A35: You are paying | D35: ='Your Deal'!$D$11 -> 255000
A36: Under / (over) your ceiling | D36: =IF('Your Deal'!$D$11=0,"",'Comps & Buy Box'!$D$33-'Your Deal'!$D$11) -> 21826.143
A38: Green means the deal clears your profit target at these numbers. Red means it does not.

Sheet Scope & Phases
A1: Scope & Phases
A2: Everything a flip can need is already listed. Untick what this house does not.
A6: Pre-ticked for a medium-scope flip. Put an x to include a job, clear the cell to drop it. Budget and days fill in from your bids.
A7: Ph | B7: Phase | C7: Category | D7: Use? | E7: Budget | F7: Days
A8: A | B8: Pre-Construction & General Conditions | C8: Permits & Plan Review | D8: x | E8: ='Bid Comparison'!N8 -> 1275 | F8: ='Bid Comparison'!O8 -> 12 | H8: =IF(D8="x",A8&"-"&COUNTIFS($A$8:A8,A8,$D$8:D8,"x"),"") -> A-1
A9: A | C9: Design & Drafting | E9: ='Bid Comparison'!N9 -> 0 | F9: ='Bid Comparison'!O9 -> 0 | H9: =IF(D9="x",A9&"-"&COUNTIFS($A$8:A9,A9,$D$8:D9,"x"),"")
A10: A | C10: Feasibility & Inspections | D10: x | E10: ='Bid Comparison'!N10 -> 750 | F10: ='Bid Comparison'!O10 -> 4 | H10: =IF(D10="x",A10&"-"&COUNTIFS($A$8:A10,A10,$D$8:D10,"x"),"") -> A-2
A11: A | C11: Impact & Utility Connection Fees | E11: ='Bid Comparison'!N11 -> 0 | F11: ='Bid Comparison'!O11 -> 0 | H11: =IF(D11="x",A11&"-"&COUNTIFS($A$8:A11,A11,$D$8:D11,"x"),"")
A12: A | C12: Insurance | D12: x | E12: ='Bid Comparison'!N12 -> 1675 | F12: ='Bid Comparison'!O12 -> 0 | H12: =IF(D12="x",A12&"-"&COUNTIFS($A$8:A12,A12,$D$8:D12,"x"),"") -> A-3
A13: A | C13: Utility Setup & Deposits | D13: x | E13: ='Bid Comparison'!N13 -> 400 | F13: ='Bid Comparison'!O13 -> 0 | H13: =IF(D13="x",A13&"-"&COUNTIFS($A$8:A13,A13,$D$8:D13,"x"),"") -> A-4
A14: A | C14: General Conditions & Supervision | D14: x | E14: ='Bid Comparison'!N14 -> 4225 | F14: ='Bid Comparison'!O14 -> 0 | H14: =IF(D14="x",A14&"-"&COUNTIFS($A$8:A14,A14,$D$8:D14,"x"),"") -> A-5
A15: A | C15: Contingency Reserve | D15: x | E15: ='Bid Comparison'!N15 -> 6600 | F15: ='Bid Comparison'!O15 -> 0 | H15: =IF(D15="x",A15&"-"&COUNTIFS($A$8:A15,A15,$D$8:D15,"x"),"") -> A-6
A16: 1 | B16: Demolition, Foundation & Underground | C16: Mobilization | D16: x | E16: ='Bid Comparison'!N16 -> 800 | F16: ='Bid Comparison'!O16 -> 2 | H16: =IF(D16="x",A16&"-"&COUNTIFS($A$8:A16,A16,$D$8:D16,"x"),"") -> 1-1
A17: 1 | C17: Hazmat Abatement | E17: ='Bid Comparison'!N17 -> 0 | F17: ='Bid Comparison'!O17 -> 0 | H17: =IF(D17="x",A17&"-"&COUNTIFS($A$8:A17,A17,$D$8:D17,"x"),"")
A18: 1 | C18: Selective Demolition | D18: x | E18: ='Bid Comparison'!N18 -> 4750 | F18: ='Bid Comparison'!O18 -> 6 | H18: =IF(D18="x",A18&"-"&COUNTIFS($A$8:A18,A18,$D$8:D18,"x"),"") -> 1-2
A19: 1 | C19: Excavation & Grading | E19: ='Bid Comparison'!N19 -> 0 | F19: ='Bid Comparison'!O19 -> 0 | H19: =IF(D19="x",A19&"-"&COUNTIFS($A$8:A19,A19,$D$8:D19,"x"),"")
A20: 1 | C20: Foundation & Slab | E20: ='Bid Comparison'!N20 -> 0 | F20: ='Bid Comparison'!O20 -> 0 | H20: =IF(D20="x",A20&"-"&COUNTIFS($A$8:A20,A20,$D$8:D20,"x"),"")
A21: 1 | C21: Underground Plumbing | E21: ='Bid Comparison'!N21 -> 0 | F21: ='Bid Comparison'!O21 -> 0 | H21: =IF(D21="x",A21&"-"&COUNTIFS($A$8:A21,A21,$D$8:D21,"x"),"")
A22: 1 | C22: Septic | E22: ='Bid Comparison'!N22 -> 0 | F22: ='Bid Comparison'!O22 -> 0 | H22: =IF(D22="x",A22&"-"&COUNTIFS($A$8:A22,A22,$D$8:D22,"x"),"")
A23: 1 | C23: Underground Electrical & Service | E23: ='Bid Comparison'!N23 -> 0 | F23: ='Bid Comparison'!O23 -> 0 | H23: =IF(D23="x",A23&"-"&COUNTIFS($A$8:A23,A23,$D$8:D23,"x"),"")
A24: 1 | C24: Pest & Soil Treatment | D24: x | E24: ='Bid Comparison'!N24 -> 450 | F24: ='Bid Comparison'!O24 -> 1 | H24: =IF(D24="x",A24&"-"&COUNTIFS($A$8:A24,A24,$D$8:D24,"x"),"") -> 1-3
A25: 2 | B25: Framing, Roofing & Rough MEP | C25: Framing Labor | D25: x | E25: ='Bid Comparison'!N25 -> 3350 | F25: ='Bid Comparison'!O25 -> 6 | H25: =IF(D25="x",A25&"-"&COUNTIFS($A$8:A25,A25,$D$8:D25,"x"),"") -> 2-1
A26: 2 | C26: Framing Material | D26: x | E26: ='Bid Comparison'!N26 -> 2725 | F26: ='Bid Comparison'!O26 -> 2 | H26: =IF(D26="x",A26&"-"&COUNTIFS($A$8:A26,A26,$D$8:D26,"x"),"") -> 2-2
A27: 2 | C27: Structural Steel & Beams | E27: ='Bid Comparison'!N27 -> 0 | F27: ='Bid Comparison'!O27 -> 0 | H27: =IF(D27="x",A27&"-"&COUNTIFS($A$8:A27,A27,$D$8:D27,"x"),"")
A28: 2 | C28: Roofing | D28: x | E28: ='Bid Comparison'!N28 -> 6950 | F28: ='Bid Comparison'!O28 -> 4 | H28: =IF(D28="x",A28&"-"&COUNTIFS($A$8:A28,A28,$D$8:D28,"x"),"") -> 2-3
A29: 2 | C29: Windows & Exterior Doors | D29: x | E29: ='Bid Comparison'!N29 -> 5450 | F29: ='Bid Comparison'!O29 -> 3 | H29: =IF(D29="x",A29&"-"&COUNTIFS($A$8:A29,A29,$D$8:D29,"x"),"") -> 2-4
A30: 2 | C30: Rough Plumbing | D30: x | E30: ='Bid Comparison'!N30 -> 3875 | F30: ='Bid Comparison'!O30 -> 5 | H30: =IF(D30="x",A30&"-"&COUNTIFS($A$8:A30,A30,$D$8:D30,"x"),"") -> 2-5
A31: 2 | C31: Rough Electrical | D31: x | E31: ='Bid Comparison'!N31 -> 4300 | F31: ='Bid Comparison'!O31 -> 6 | H31: =IF(D31="x",A31&"-"&COUNTIFS($A$8:A31,A31,$D$8:D31,"x"),"") -> 2-6
A32: 2 | C32: Rough HVAC | D32: x | E32: ='Bid Comparison'!N32 -> 5975 | F32: ='Bid Comparison'!O32 -> 4 | H32: =IF(D32="x",A32&"-"&COUNTIFS($A$8:A32,A32,$D$8:D32,"x"),"") -> 2-7
A33: 2 | C33: Low Voltage Rough | E33: ='Bid Comparison'!N33 -> 0 | F33: ='Bid Comparison'!O33 -> 0 | H33: =IF(D33="x",A33&"-"&COUNTIFS($A$8:A33,A33,$D$8:D33,"x"),"")
A34: 2 | C34: Rough Inspections | D34: x | E34: ='Bid Comparison'!N34 -> 300 | F34: ='Bid Comparison'!O34 -> 3 | H34: =IF(D34="x",A34&"-"&COUNTIFS($A$8:A34,A34,$D$8:D34,"x"),"") -> 2-8
A35: 3 | B35: Insulation, Drywall, Doors, Trim & Paint | C35: Insulation | D35: x | E35: ='Bid Comparison'!N35 -> 1850 | F35: ='Bid Comparison'!O35 -> 2 | H35: =IF(D35="x",A35&"-"&COUNTIFS($A$8:A35,A35,$D$8:D35,"x"),"") -> 3-1
A36: 3 | C36: Drywall | D36: x | E36: ='Bid Comparison'!N36 -> 5625 | F36: ='Bid Comparison'!O36 -> 8 | H36: =IF(D36="x",A36&"-"&COUNTIFS($A$8:A36,A36,$D$8:D36,"x"),"") -> 3-2
A37: 3 | C37: Interior Doors | D37: x | E37: ='Bid Comparison'!N37 -> 2025 | F37: ='Bid Comparison'!O37 -> 3 | H37: =IF(D37="x",A37&"-"&COUNTIFS($A$8:A37,A37,$D$8:D37,"x"),"") -> 3-3
A38: 3 | C38: Trim & Millwork | D38: x | E38: ='Bid Comparison'!N38 -> 2550 | F38: ='Bid Comparison'!O38 -> 4 | H38: =IF(D38="x",A38&"-"&COUNTIFS($A$8:A38,A38,$D$8:D38,"x"),"") -> 3-4
A39: 3 | C39: Stairs & Railings | E39: ='Bid Comparison'!N39 -> 0 | F39: ='Bid Comparison'!O39 -> 0 | H39: =IF(D39="x",A39&"-"&COUNTIFS($A$8:A39,A39,$D$8:D39,"x"),"")
A40: 3 | C40: Interior Paint | D40: x | E40: ='Bid Comparison'!N40 -> 4050 | F40: ='Bid Comparison'!O40 -> 5 | H40: =IF(D40="x",A40&"-"&COUNTIFS($A$8:A40,A40,$D$8:D40,"x"),"") -> 3-5
A41: 4 | B41: Cabinets & Countertops | C41: Kitchen Cabinets | D41: x | E41: ='Bid Comparison'!N41 -> 6075 | F41: ='Bid Comparison'!O41 -> 4 | H41: =IF(D41="x",A41&"-"&COUNTIFS($A$8:A41,A41,$D$8:D41,"x"),"") -> 4-1
A42: 4 | C42: Bath Vanities | D42: x | E42: ='Bid Comparison'!N42 -> 1625 | F42: ='Bid Comparison'!O42 -> 2 | H42: =IF(D42="x",A42&"-"&COUNTIFS($A$8:A42,A42,$D$8:D42,"x"),"") -> 4-2
A43: 4 | C43: Laundry & Utility Cabinets | D43: x | E43: ='Bid Comparison'!N43 -> 675 | F43: ='Bid Comparison'!O43 -> 1 | H43: =IF(D43="x",A43&"-"&COUNTIFS($A$8:A43,A43,$D$8:D43,"x"),"") -> 4-3
A44: 4 | C44: Closet Systems | E44: ='Bid Comparison'!N44 -> 0 | F44: ='Bid Comparison'!O44 -> 0 | H44: =IF(D44="x",A44&"-"&COUNTIFS($A$8:A44,A44,$D$8:D44,"x"),"")
A45: 4 | C45: Countertops | D45: x | E45: ='Bid Comparison'!N45 -> 3700 | F45: ='Bid Comparison'!O45 -> 3 | H45: =IF(D45="x",A45&"-"&COUNTIFS($A$8:A45,A45,$D$8:D45,"x"),"") -> 4-4
A46: 4 | C46: Cabinet Hardware | D46: x | E46: ='Bid Comparison'!N46 -> 550 | F46: ='Bid Comparison'!O46 -> 1 | H46: =IF(D46="x",A46&"-"&COUNTIFS($A$8:A46,A46,$D$8:D46,"x"),"") -> 4-5
A47: 5 | B47: Tile & Flooring | C47: Floor Prep & Leveling | D47: x | E47: ='Bid Comparison'!N47 -> 925 | F47: ='Bid Comparison'!O47 -> 2 | H47: =IF(D47="x",A47&"-"&COUNTIFS($A$8:A47,A47,$D$8:D47,"x"),"") -> 5-1
A48: 5 | C48: Floor Tile | D48: x | E48: ='Bid Comparison'!N48 -> 3000 | F48: ='Bid Comparison'!O48 -> 4 | H48: =IF(D48="x",A48&"-"&COUNTIFS($A$8:A48,A48,$D$8:D48,"x"),"") -> 5-2
A49: 5 | C49: Shower & Tub Surround Tile | D49: x | E49: ='Bid Comparison'!N49 -> 2475 | F49: ='Bid Comparison'!O49 -> 4 | H49: =IF(D49="x",A49&"-"&COUNTIFS($A$8:A49,A49,$D$8:D49,"x"),"") -> 5-3
A50: 5 | C50: Backsplash Tile | D50: x | E50: ='Bid Comparison'!N50 -> 1000 | F50: ='Bid Comparison'!O50 -> 2 | H50: =IF(D50="x",A50&"-"&COUNTIFS($A$8:A50,A50,$D$8:D50,"x"),"") -> 5-4
A51: 5 | C51: LVP / Hardwood / Laminate | D51: x | E51: ='Bid Comparison'!N51 -> 5200 | F51: ='Bid Comparison'!O51 -> 4 | H51: =IF(D51="x",A51&"-"&COUNTIFS($A$8:A51,A51,$D$8:D51,"x"),"") -> 5-5
A52: 5 | C52: Grout, Sealer & Trim Pieces | D52: x | E52: ='Bid Comparison'!N52 -> 450 | F52: ='Bid Comparison'!O52 -> 1 | H52: =IF(D52="x",A52&"-"&COUNTIFS($A$8:A52,A52,$D$8:D52,"x"),"") -> 5-6
A53: 6 | B53: Exterior & Landscaping | C53: Stucco / Siding | D53: x | E53: ='Bid Comparison'!N53 -> 2900 | F53: ='Bid Comparison'!O53 -> 5 | H53: =IF(D53="x",A53&"-"&COUNTIFS($A$8:A53,A53,$D$8:D53,"x"),"") -> 6-1
A54: 6 | C54: Fascia, Soffit & Gutters | D54: x | E54: ='Bid Comparison'!N54 -> 1400 | F54: ='Bid Comparison'!O54 -> 3 | H54: =IF(D54="x",A54&"-"&COUNTIFS($A$8:A54,A54,$D$8:D54,"x"),"") -> 6-2
A55: 6 | C55: Driveway, Walkway & Hardscape | E55: ='Bid Comparison'!N55 -> 0 | F55: ='Bid Comparison'!O55 -> 0 | H55: =IF(D55="x",A55&"-"&COUNTIFS($A$8:A55,A55,$D$8:D55,"x"),"")
A56: 6 | C56: Fencing & Gates | D56: x | E56: ='Bid Comparison'!N56 -> 2150 | F56: ='Bid Comparison'!O56 -> 3 | H56: =IF(D56="x",A56&"-"&COUNTIFS($A$8:A56,A56,$D$8:D56,"x"),"") -> 6-3
A57: 6 | C57: Pool Repair & Resurface | E57: ='Bid Comparison'!N57 -> 0 | F57: ='Bid Comparison'!O57 -> 0 | H57: =IF(D57="x",A57&"-"&COUNTIFS($A$8:A57,A57,$D$8:D57,"x"),"")
A58: 6 | C58: Exterior Paint | D58: x | E58: ='Bid Comparison'!N58 -> 3250 | F58: ='Bid Comparison'!O58 -> 4 | H58: =IF(D58="x",A58&"-"&COUNTIFS($A$8:A58,A58,$D$8:D58,"x"),"") -> 6-4
A59: 6 | C59: Exterior Lighting | D59: x | E59: ='Bid Comparison'!N59 -> 575 | F59: ='Bid Comparison'!O59 -> 1 | H59: =IF(D59="x",A59&"-"&COUNTIFS($A$8:A59,A59,$D$8:D59,"x"),"") -> 6-5
A60: 6 | C60: Landscaping | D60: x | E60: ='Bid Comparison'!N60 -> 4225 | F60: ='Bid Comparison'!O60 -> 6 | H60: =IF(D60="x",A60&"-"&COUNTIFS($A$8:A60,A60,$D$8:D60,"x"),"") -> 6-6
A61: 7 | B61: MEP Finishes, Glass & Appliances | C61: Plumbing Trim | D61: x | E61: ='Bid Comparison'!N61 -> 1750 | F61: ='Bid Comparison'!O61 -> 3 | H61: =IF(D61="x",A61&"-"&COUNTIFS($A$8:A61,A61,$D$8:D61,"x"),"") -> 7-1
A62: 7 | C62: Electrical Trim | D62: x | E62: ='Bid Comparison'!N62 -> 1550 | F62: ='Bid Comparison'!O62 -> 3 | H62: =IF(D62="x",A62&"-"&COUNTIFS($A$8:A62,A62,$D$8:D62,"x"),"") -> 7-2
A63: 7 | C63: HVAC Start-up & Registers | D63: x | E63: ='Bid Comparison'!N63 -> 700 | F63: ='Bid Comparison'!O63 -> 2 | H63: =IF(D63="x",A63&"-"&COUNTIFS($A$8:A63,A63,$D$8:D63,"x"),"") -> 7-3
A64: 7 | C64: Shower Glass & Mirrors | D64: x | E64: ='Bid Comparison'!N64 -> 1850 | F64: ='Bid Comparison'!O64 -> 2 | H64: =IF(D64="x",A64&"-"&COUNTIFS($A$8:A64,A64,$D$8:D64,"x"),"") -> 7-4
A65: 7 | C65: Bath Accessories | D65: x | E65: ='Bid Comparison'!N65 -> 450 | F65: ='Bid Comparison'!O65 -> 1 | H65: =IF(D65="x",A65&"-"&COUNTIFS($A$8:A65,A65,$D$8:D65,"x"),"") -> 7-5
A66: 7 | C66: Appliances | D66: x | E66: ='Bid Comparison'!N66 -> 4050 | F66: ='Bid Comparison'!O66 -> 1 | H66: =IF(D66="x",A66&"-"&COUNTIFS($A$8:A66,A66,$D$8:D66,"x"),"") -> 7-6
A67: 7 | C67: Garage Door & Opener | D67: x | E67: ='Bid Comparison'!N67 -> 1325 | F67: ='Bid Comparison'!O67 -> 1 | H67: =IF(D67="x",A67&"-"&COUNTIFS($A$8:A67,A67,$D$8:D67,"x"),"") -> 7-7
A68: 7 | C68: Life Safety & Final Inspections | D68: x | E68: ='Bid Comparison'!N68 -> 400 | F68: ='Bid Comparison'!O68 -> 2 | H68: =IF(D68="x",A68&"-"&COUNTIFS($A$8:A68,A68,$D$8:D68,"x"),"") -> 7-8
A69: 8 | B69: Punch, Carpet & Final Clean | C69: Punch List & Touch-up | D69: x | E69: ='Bid Comparison'!N69 -> 1400 | F69: ='Bid Comparison'!O69 -> 4 | H69: =IF(D69="x",A69&"-"&COUNTIFS($A$8:A69,A69,$D$8:D69,"x"),"") -> 8-1
A70: 8 | C70: Carpet | D70: x | E70: ='Bid Comparison'!N70 -> 1925 | F70: ='Bid Comparison'!O70 -> 2 | H70: =IF(D70="x",A70&"-"&COUNTIFS($A$8:A70,A70,$D$8:D70,"x"),"") -> 8-2
A71: 8 | C71: Final Clean | D71: x | E71: ='Bid Comparison'!N71 -> 625 | F71: ='Bid Comparison'!O71 -> 2 | H71: =IF(D71="x",A71&"-"&COUNTIFS($A$8:A71,A71,$D$8:D71,"x"),"") -> 8-3
A72: 8 | C72: Staging | D72: x | E72: ='Bid Comparison'!N72 -> 2200 | F72: ='Bid Comparison'!O72 -> 2 | H72: =IF(D72="x",A72&"-"&COUNTIFS($A$8:A72,A72,$D$8:D72,"x"),"") -> 8-4
A73: 8 | C73: Warranty & Callback Reserve | D73: x | E73: ='Bid Comparison'!N73 -> 975 | F73: ='Bid Comparison'!O73 -> 0 | H73: =IF(D73="x",A73&"-"&COUNTIFS($A$8:A73,A73,$D$8:D73,"x"),"") -> 8-5
C74: Jobs included | D74: =COUNTIF(D8:D73,"x") -> 52 | E74: =SUMIF($D$8:$D$73,"x",$E$8:$E$73) -> 129325

Sheet Bid Request
A1: Bid Request | H1: A — Pre-Construction & General Conditions
A2: Pick a phase, print this page, hand it to a sub. They fill in price and days. | H2: 1 — Demolition, Foundation & Underground
H3: 2 — Framing, Roofing & Rough MEP
H4: 3 — Insulation, Drywall, Doors, Trim & Paint
H5: 4 — Cabinets & Countertops
A6: Which phase are you sending out? | B6: 2 — Framing, Roofing & Rough MEP | C6: =HYPERLINK("mailto:?subject="&SUBSTITUTE(SUBSTITUTE("Bid request - "&$B$8&" - "&$B$6,"&","%26")," ","%20")&"&body="&SUBSTITUTE(SUBSTITUTE("Hi,"&"%0D%0A"&"%0D%0A"&"I am requesting a bid on the scope below for "&$B$8&"."&"%0D%0A"&"%0D%0A"&"Phase: "&$B$6&"%0D%0A"&"%0D%0A"&_xlfn.TEXTJOIN("%0D%0A",TRUE,A16:A27)&"%0D%0A"&"%0D%0A"&"Please reply with a price and the number of calendar days for each line."&"%0D%0A"&"%0D%0A"&"Terms: a deposit at start of work with the balance on completion. Days are calendar days. Price includes labor and materials unless you note otherwise. A signed lien waiver is required with each payment."&"%0D%0A"&"%0D%0A"&"Thank you,","&","%26")," ","%20"),"✉ Email this bid request") -> #VALUE! | H6: 5 — Tile & Flooring
C7: Opens your mail app with the whole request written. Add their address and send. | H7: 6 — Exterior & Landscaping
A8: Property | B8: ='Your Deal'!$D$7 -> 1421 E Cloud Rd, Queen Creek AZ | H8: 7 — MEP Finishes, Glass & Appliances
A9: Contractor / sub | H9: 8 — Punch, Carpet & Final Clean
A10: Date sent
A11: Please return by
A13: SCOPE OF WORK
A15: Category | B15: Describe the work (you fill this in) | C15: Your price | D15: Days
A16: =IFERROR(INDEX('Scope & Phases'!$C$8:$C$73,MATCH(LEFT($B$6,FIND(" ",$B$6&" ")-1)&"-"&1,'Scope & Phases'!$H$8:$H$73,0)),"") -> Framing Labor
A17: =IFERROR(INDEX('Scope & Phases'!$C$8:$C$73,MATCH(LEFT($B$6,FIND(" ",$B$6&" ")-1)&"-"&2,'Scope & Phases'!$H$8:$H$73,0)),"") -> Framing Material
A18: =IFERROR(INDEX('Scope & Phases'!$C$8:$C$73,MATCH(LEFT($B$6,FIND(" ",$B$6&" ")-1)&"-"&3,'Scope & Phases'!$H$8:$H$73,0)),"") -> Roofing
A19: =IFERROR(INDEX('Scope & Phases'!$C$8:$C$73,MATCH(LEFT($B$6,FIND(" ",$B$6&" ")-1)&"-"&4,'Scope & Phases'!$H$8:$H$73,0)),"") -> Windows & Exterior Doors
A20: =IFERROR(INDEX('Scope & Phases'!$C$8:$C$73,MATCH(LEFT($B$6,FIND(" ",$B$6&" ")-1)&"-"&5,'Scope & Phases'!$H$8:$H$73,0)),"") -> Rough Plumbing
A21: =IFERROR(INDEX('Scope & Phases'!$C$8:$C$73,MATCH(LEFT($B$6,FIND(" ",$B$6&" ")-1)&"-"&6,'Scope & Phases'!$H$8:$H$73,0)),"") -> Rough Electrical
A22: =IFERROR(INDEX('Scope & Phases'!$C$8:$C$73,MATCH(LEFT($B$6,FIND(" ",$B$6&" ")-1)&"-"&7,'Scope & Phases'!$H$8:$H$73,0)),"") -> Rough HVAC
A23: =IFERROR(INDEX('Scope & Phases'!$C$8:$C$73,MATCH(LEFT($B$6,FIND(" ",$B$6&" ")-1)&"-"&8,'Scope & Phases'!$H$8:$H$73,0)),"") -> Rough Inspections
A24: =IFERROR(INDEX('Scope & Phases'!$C$8:$C$73,MATCH(LEFT($B$6,FIND(" ",$B$6&" ")-1)&"-"&9,'Scope & Phases'!$H$8:$H$73,0)),"")
A25: =IFERROR(INDEX('Scope & Phases'!$C$8:$C$73,MATCH(LEFT($B$6,FIND(" ",$B$6&" ")-1)&"-"&10,'Scope & Phases'!$H$8:$H$73,0)),"")
A26: =IFERROR(INDEX('Scope & Phases'!$C$8:$C$73,MATCH(LEFT($B$6,FIND(" ",$B$6&" ")-1)&"-"&11,'Scope & Phases'!$H$8:$H$73,0)),"")
A27: =IFERROR(INDEX('Scope & Phases'!$C$8:$C$73,MATCH(LEFT($B$6,FIND(" ",$B$6&" ")-1)&"-"&12,'Scope & Phases'!$H$8:$H$73,0)),"")
B29: TOTAL BID | C29: =SUM(C16:C27) -> 0 | D29: =IFERROR(MAX(D16:D27),0) -> 0
A31: TERMS
A33: • Deposit at start of work: this project pays a deposit, with the balance due on completion.
A34: • Days above are calendar days from the day you start, not working days.
A35: • Price is for labor and materials unless you note otherwise in the description.
A36: • A signed lien waiver is required with each payment.
A38: Questions about this request? support@honafinancial.com

Sheet Bid Comparison
A1: Bid Comparison
A2: Type in what each sub quoted. The cheapest is used unless you pick another.
A6: One bid gets you a budget. Three gets you the truth. Days come from the sub, not from you — leave Days at 0 for anything that runs the whole job, like supervision, insurance or a reserve.
A7: Ph | B7: Category | C7: Use? | D7: Bid 1 — company | E7: Bid 1 $ | F7: Days | G7: Bid 2 — company | H7: Bid 2 $ | I7: Days | J7: Bid 3 — company | K7: Bid 3 $ | L7: Days | M7: Pick | N7: Chosen $ | O7: Days | P7: Chosen sub
A8: A | B8: Permits & Plan Review | C8: ='Scope & Phases'!D8 -> x | D8: City of Queen Creek | E8: 1275 | F8: 12 | N8: =IFERROR(IF($C8<>"x",0,IF($M8=1,E8,IF($M8=2,H8,IF($M8=3,K8,IF(COUNT(E8,H8,K8)=0,0,MIN(IF(E8>0,E8,1E+99),IF(H8>0,H8,1E+99),IF(K8>0,K8,1E+99))))))),0) -> 1275 | O8: =IFERROR(IF($C8<>"x",0,IF($M8=1,F8,IF($M8=2,I8,IF($M8=3,L8,IF(E8=IF(COUNT(E8,H8,K8)=0,0,MIN(IF(E8>0,E8,1E+99),IF(H8>0,H8,1E+99),IF(K8>0,K8,1E+99))),F8,IF(H8=IF(COUNT(E8,H8,K8)=0,0,MIN(IF(E8>0,E8,1E+99),IF(H8>0,H8,1E+99),IF(K8>0,K8,1E+99))),I8,L8)))))),0) -> 12 | P8: =IFERROR(IF($C8<>"x",0,IF($M8=1,D8,IF($M8=2,G8,IF($M8=3,J8,IF(E8=IF(COUNT(E8,H8,K8)=0,0,MIN(IF(E8>0,E8,1E+99),IF(H8>0,H8,1E+99),IF(K8>0,K8,1E+99))),D8,IF(H8=IF(COUNT(E8,H8,K8)=0,0,MIN(IF(E8>0,E8,1E+99),IF(H8>0,H8,1E+99),IF(K8>0,K8,1E+99))),G8,J8)))))),0) -> City of Queen Creek
A9: A | B9: Design & Drafting | C9: ='Scope & Phases'!D9 -> 0 | N9: =IFERROR(IF($C9<>"x",0,IF($M9=1,E9,IF($M9=2,H9,IF($M9=3,K9,IF(COUNT(E9,H9,K9)=0,0,MIN(IF(E9>0,E9,1E+99),IF(H9>0,H9,1E+99),IF(K9>0,K9,1E+99))))))),0) -> 0 | O9: =IFERROR(IF($C9<>"x",0,IF($M9=1,F9,IF($M9=2,I9,IF($M9=3,L9,IF(E9=IF(COUNT(E9,H9,K9)=0,0,MIN(IF(E9>0,E9,1E+99),IF(H9>0,H9,1E+99),IF(K9>0,K9,1E+99))),F9,IF(H9=IF(COUNT(E9,H9,K9)=0,0,MIN(IF(E9>0,E9,1E+99),IF(H9>0,H9,1E+99),IF(K9>0,K9,1E+99))),I9,L9)))))),0) -> 0 | P9: =IFERROR(IF($C9<>"x",0,IF($M9=1,D9,IF($M9=2,G9,IF($M9=3,J9,IF(E9=IF(COUNT(E9,H9,K9)=0,0,MIN(IF(E9>0,E9,1E+99),IF(H9>0,H9,1E+99),IF(K9>0,K9,1E+99))),D9,IF(H9=IF(COUNT(E9,H9,K9)=0,0,MIN(IF(E9>0,E9,1E+99),IF(H9>0,H9,1E+99),IF(K9>0,K9,1E+99))),G9,J9)))))),0) -> 0
A10: A | B10: Feasibility & Inspections | C10: ='Scope & Phases'!D10 -> x | E10: 750 | F10: 4 | N10: =IFERROR(IF($C10<>"x",0,IF($M10=1,E10,IF($M10=2,H10,IF($M10=3,K10,IF(COUNT(E10,H10,K10)=0,0,MIN(IF(E10>0,E10,1E+99),IF(H10>0,H10,1E+99),IF(K10>0,K10,1E+99))))))),0) -> 750 | O10: =IFERROR(IF($C10<>"x",0,IF($M10=1,F10,IF($M10=2,I10,IF($M10=3,L10,IF(E10=IF(COUNT(E10,H10,K10)=0,0,MIN(IF(E10>0,E10,1E+99),IF(H10>0,H10,1E+99),IF(K10>0,K10,1E+99))),F10,IF(H10=IF(COUNT(E10,H10,K10)=0,0,MIN(IF(E10>0,E10,1E+99),IF(H10>0,H10,1E+99),IF(K10>0,K10,1E+99))),I10,L10)))))),0) -> 4 | P10: =IFERROR(IF($C10<>"x",0,IF($M10=1,D10,IF($M10=2,G10,IF($M10=3,J10,IF(E10=IF(COUNT(E10,H10,K10)=0,0,MIN(IF(E10>0,E10,1E+99),IF(H10>0,H10,1E+99),IF(K10>0,K10,1E+99))),D10,IF(H10=IF(COUNT(E10,H10,K10)=0,0,MIN(IF(E10>0,E10,1E+99),IF(H10>0,H10,1E+99),IF(K10>0,K10,1E+99))),G10,J10)))))),0) -> 0
A11: A | B11: Impact & Utility Connection Fees | C11: ='Scope & Phases'!D11 -> 0 | N11: =IFERROR(IF($C11<>"x",0,IF($M11=1,E11,IF($M11=2,H11,IF($M11=3,K11,IF(COUNT(E11,H11,K11)=0,0,MIN(IF(E11>0,E11,1E+99),IF(H11>0,H11,1E+99),IF(K11>0,K11,1E+99))))))),0) -> 0 | O11: =IFERROR(IF($C11<>"x",0,IF($M11=1,F11,IF($M11=2,I11,IF($M11=3,L11,IF(E11=IF(COUNT(E11,H11,K11)=0,0,MIN(IF(E11>0,E11,1E+99),IF(H11>0,H11,1E+99),IF(K11>0,K11,1E+99))),F11,IF(H11=IF(COUNT(E11,H11,K11)=0,0,MIN(IF(E11>0,E11,1E+99),IF(H11>0,H11,1E+99),IF(K11>0,K11,1E+99))),I11,L11)))))),0) -> 0 | P11: =IFERROR(IF($C11<>"x",0,IF($M11=1,D11,IF($M11=2,G11,IF($M11=3,J11,IF(E11=IF(COUNT(E11,H11,K11)=0,0,MIN(IF(E11>0,E11,1E+99),IF(H11>0,H11,1E+99),IF(K11>0,K11,1E+99))),D11,IF(H11=IF(COUNT(E11,H11,K11)=0,0,MIN(IF(E11>0,E11,1E+99),IF(H11>0,H11,1E+99),IF(K11>0,K11,1E+99))),G11,J11)))))),0) -> 0
A12: A | B12: Insurance | C12: ='Scope & Phases'!D12 -> x | D12: Hartford | E12: 1675 | F12: 0 | N12: =IFERROR(IF($C12<>"x",0,IF($M12=1,E12,IF($M12=2,H12,IF($M12=3,K12,IF(COUNT(E12,H12,K12)=0,0,MIN(IF(E12>0,E12,1E+99),IF(H12>0,H12,1E+99),IF(K12>0,K12,1E+99))))))),0) -> 1675 | O12: =IFERROR(IF($C12<>"x",0,IF($M12=1,F12,IF($M12=2,I12,IF($M12=3,L12,IF(E12=IF(COUNT(E12,H12,K12)=0,0,MIN(IF(E12>0,E12,1E+99),IF(H12>0,H12,1E+99),IF(K12>0,K12,1E+99))),F12,IF(H12=IF(COUNT(E12,H12,K12)=0,0,MIN(IF(E12>0,E12,1E+99),IF(H12>0,H12,1E+99),IF(K12>0,K12,1E+99))),I12,L12)))))),0) -> 0 | P12: =IFERROR(IF($C12<>"x",0,IF($M12=1,D12,IF($M12=2,G12,IF($M12=3,J12,IF(E12=IF(COUNT(E12,H12,K12)=0,0,MIN(IF(E12>0,E12,1E+99),IF(H12>0,H12,1E+99),IF(K12>0,K12,1E+99))),D12,IF(H12=IF(COUNT(E12,H12,K12)=0,0,MIN(IF(E12>0,E12,1E+99),IF(H12>0,H12,1E+99),IF(K12>0,K12,1E+99))),G12,J12)))))),0) -> Hartford
A13: A | B13: Utility Setup & Deposits | C13: ='Scope & Phases'!D13 -> x | E13: 400 | F13: 0 | N13: =IFERROR(IF($C13<>"x",0,IF($M13=1,E13,IF($M13=2,H13,IF($M13=3,K13,IF(COUNT(E13,H13,K13)=0,0,MIN(IF(E13>0,E13,1E+99),IF(H13>0,H13,1E+99),IF(K13>0,K13,1E+99))))))),0) -> 400 | O13: =IFERROR(IF($C13<>"x",0,IF($M13=1,F13,IF($M13=2,I13,IF($M13=3,L13,IF(E13=IF(COUNT(E13,H13,K13)=0,0,MIN(IF(E13>0,E13,1E+99),IF(H13>0,H13,1E+99),IF(K13>0,K13,1E+99))),F13,IF(H13=IF(COUNT(E13,H13,K13)=0,0,MIN(IF(E13>0,E13,1E+99),IF(H13>0,H13,1E+99),IF(K13>0,K13,1E+99))),I13,L13)))))),0) -> 0 | P13: =IFERROR(IF($C13<>"x",0,IF($M13=1,D13,IF($M13=2,G13,IF($M13=3,J13,IF(E13=IF(COUNT(E13,H13,K13)=0,0,MIN(IF(E13>0,E13,1E+99),IF(H13>0,H13,1E+99),IF(K13>0,K13,1E+99))),D13,IF(H13=IF(COUNT(E13,H13,K13)=0,0,MIN(IF(E13>0,E13,1E+99),IF(H13>0,H13,1E+99),IF(K13>0,K13,1E+99))),G13,J13)))))),0) -> 0
A14: A | B14: General Conditions & Supervision | C14: ='Scope & Phases'!D14 -> x | E14: 4225 | F14: 0 | N14: =IFERROR(IF($C14<>"x",0,IF($M14=1,E14,IF($M14=2,H14,IF($M14=3,K14,IF(COUNT(E14,H14,K14)=0,0,MIN(IF(E14>0,E14,1E+99),IF(H14>0,H14,1E+99),IF(K14>0,K14,1E+99))))))),0) -> 4225 | O14: =IFERROR(IF($C14<>"x",0,IF($M14=1,F14,IF($M14=2,I14,IF($M14=3,L14,IF(E14=IF(COUNT(E14,H14,K14)=0,0,MIN(IF(E14>0,E14,1E+99),IF(H14>0,H14,1E+99),IF(K14>0,K14,1E+99))),F14,IF(H14=IF(COUNT(E14,H14,K14)=0,0,MIN(IF(E14>0,E14,1E+99),IF(H14>0,H14,1E+99),IF(K14>0,K14,1E+99))),I14,L14)))))),0) -> 0 | P14: =IFERROR(IF($C14<>"x",0,IF($M14=1,D14,IF($M14=2,G14,IF($M14=3,J14,IF(E14=IF(COUNT(E14,H14,K14)=0,0,MIN(IF(E14>0,E14,1E+99),IF(H14>0,H14,1E+99),IF(K14>0,K14,1E+99))),D14,IF(H14=IF(COUNT(E14,H14,K14)=0,0,MIN(IF(E14>0,E14,1E+99),IF(H14>0,H14,1E+99),IF(K14>0,K14,1E+99))),G14,J14)))))),0) -> 0
A15: A | B15: Contingency Reserve | C15: ='Scope & Phases'!D15 -> x | E15: 6600 | F15: 0 | N15: =IFERROR(IF($C15<>"x",0,IF($M15=1,E15,IF($M15=2,H15,IF($M15=3,K15,IF(COUNT(E15,H15,K15)=0,0,MIN(IF(E15>0,E15,1E+99),IF(H15>0,H15,1E+99),IF(K15>0,K15,1E+99))))))),0) -> 6600 | O15: =IFERROR(IF($C15<>"x",0,IF($M15=1,F15,IF($M15=2,I15,IF($M15=3,L15,IF(E15=IF(COUNT(E15,H15,K15)=0,0,MIN(IF(E15>0,E15,1E+99),IF(H15>0,H15,1E+99),IF(K15>0,K15,1E+99))),F15,IF(H15=IF(COUNT(E15,H15,K15)=0,0,MIN(IF(E15>0,E15,1E+99),IF(H15>0,H15,1E+99),IF(K15>0,K15,1E+99))),I15,L15)))))),0) -> 0 | P15: =IFERROR(IF($C15<>"x",0,IF($M15=1,D15,IF($M15=2,G15,IF($M15=3,J15,IF(E15=IF(COUNT(E15,H15,K15)=0,0,MIN(IF(E15>0,E15,1E+99),IF(H15>0,H15,1E+99),IF(K15>0,K15,1E+99))),D15,IF(H15=IF(COUNT(E15,H15,K15)=0,0,MIN(IF(E15>0,E15,1E+99),IF(H15>0,H15,1E+99),IF(K15>0,K15,1E+99))),G15,J15)))))),0) -> 0
A16: 1 | B16: Mobilization | C16: ='Scope & Phases'!D16 -> x | E16: 800 | F16: 2 | N16: =IFERROR(IF($C16<>"x",0,IF($M16=1,E16,IF($M16=2,H16,IF($M16=3,K16,IF(COUNT(E16,H16,K16)=0,0,MIN(IF(E16>0,E16,1E+99),IF(H16>0,H16,1E+99),IF(K16>0,K16,1E+99))))))),0) -> 800 | O16: =IFERROR(IF($C16<>"x",0,IF($M16=1,F16,IF($M16=2,I16,IF($M16=3,L16,IF(E16=IF(COUNT(E16,H16,K16)=0,0,MIN(IF(E16>0,E16,1E+99),IF(H16>0,H16,1E+99),IF(K16>0,K16,1E+99))),F16,IF(H16=IF(COUNT(E16,H16,K16)=0,0,MIN(IF(E16>0,E16,1E+99),IF(H16>0,H16,1E+99),IF(K16>0,K16,1E+99))),I16,L16)))))),0) -> 2 | P16: =IFERROR(IF($C16<>"x",0,IF($M16=1,D16,IF($M16=2,G16,IF($M16=3,J16,IF(E16=IF(COUNT(E16,H16,K16)=0,0,MIN(IF(E16>0,E16,1E+99),IF(H16>0,H16,1E+99),IF(K16>0,K16,1E+99))),D16,IF(H16=IF(COUNT(E16,H16,K16)=0,0,MIN(IF(E16>0,E16,1E+99),IF(H16>0,H16,1E+99),IF(K16>0,K16,1E+99))),G16,J16)))))),0) -> 0
A17: 1 | B17: Hazmat Abatement | C17: ='Scope & Phases'!D17 -> 0 | N17: =IFERROR(IF($C17<>"x",0,IF($M17=1,E17,IF($M17=2,H17,IF($M17=3,K17,IF(COUNT(E17,H17,K17)=0,0,MIN(IF(E17>0,E17,1E+99),IF(H17>0,H17,1E+99),IF(K17>0,K17,1E+99))))))),0) -> 0 | O17: =IFERROR(IF($C17<>"x",0,IF($M17=1,F17,IF($M17=2,I17,IF($M17=3,L17,IF(E17=IF(COUNT(E17,H17,K17)=0,0,MIN(IF(E17>0,E17,1E+99),IF(H17>0,H17,1E+99),IF(K17>0,K17,1E+99))),F17,IF(H17=IF(COUNT(E17,H17,K17)=0,0,MIN(IF(E17>0,E17,1E+99),IF(H17>0,H17,1E+99),IF(K17>0,K17,1E+99))),I17,L17)))))),0) -> 0 | P17: =IFERROR(IF($C17<>"x",0,IF($M17=1,D17,IF($M17=2,G17,IF($M17=3,J17,IF(E17=IF(COUNT(E17,H17,K17)=0,0,MIN(IF(E17>0,E17,1E+99),IF(H17>0,H17,1E+99),IF(K17>0,K17,1E+99))),D17,IF(H17=IF(COUNT(E17,H17,K17)=0,0,MIN(IF(E17>0,E17,1E+99),IF(H17>0,H17,1E+99),IF(K17>0,K17,1E+99))),G17,J17)))))),0) -> 0
A18: 1 | B18: Selective Demolition | C18: ='Scope & Phases'!D18 -> x | D18: Demo Pros LLC | E18: 4750 | F18: 6 | N18: =IFERROR(IF($C18<>"x",0,IF($M18=1,E18,IF($M18=2,H18,IF($M18=3,K18,IF(COUNT(E18,H18,K18)=0,0,MIN(IF(E18>0,E18,1E+99),IF(H18>0,H18,1E+99),IF(K18>0,K18,1E+99))))))),0) -> 4750 | O18: =IFERROR(IF($C18<>"x",0,IF($M18=1,F18,IF($M18=2,I18,IF($M18=3,L18,IF(E18=IF(COUNT(E18,H18,K18)=0,0,MIN(IF(E18>0,E18,1E+99),IF(H18>0,H18,1E+99),IF(K18>0,K18,1E+99))),F18,IF(H18=IF(COUNT(E18,H18,K18)=0,0,MIN(IF(E18>0,E18,1E+99),IF(H18>0,H18,1E+99),IF(K18>0,K18,1E+99))),I18,L18)))))),0) -> 6 | P18: =IFERROR(IF($C18<>"x",0,IF($M18=1,D18,IF($M18=2,G18,IF($M18=3,J18,IF(E18=IF(COUNT(E18,H18,K18)=0,0,MIN(IF(E18>0,E18,1E+99),IF(H18>0,H18,1E+99),IF(K18>0,K18,1E+99))),D18,IF(H18=IF(COUNT(E18,H18,K18)=0,0,MIN(IF(E18>0,E18,1E+99),IF(H18>0,H18,1E+99),IF(K18>0,K18,1E+99))),G18,J18)))))),0) -> Demo Pros LLC
A19: 1 | B19: Excavation & Grading | C19: ='Scope & Phases'!D19 -> 0 | N19: =IFERROR(IF($C19<>"x",0,IF($M19=1,E19,IF($M19=2,H19,IF($M19=3,K19,IF(COUNT(E19,H19,K19)=0,0,MIN(IF(E19>0,E19,1E+99),IF(H19>0,H19,1E+99),IF(K19>0,K19,1E+99))))))),0) -> 0 | O19: =IFERROR(IF($C19<>"x",0,IF($M19=1,F19,IF($M19=2,I19,IF($M19=3,L19,IF(E19=IF(COUNT(E19,H19,K19)=0,0,MIN(IF(E19>0,E19,1E+99),IF(H19>0,H19,1E+99),IF(K19>0,K19,1E+99))),F19,IF(H19=IF(COUNT(E19,H19,K19)=0,0,MIN(IF(E19>0,E19,1E+99),IF(H19>0,H19,1E+99),IF(K19>0,K19,1E+99))),I19,L19)))))),0) -> 0 | P19: =IFERROR(IF($C19<>"x",0,IF($M19=1,D19,IF($M19=2,G19,IF($M19=3,J19,IF(E19=IF(COUNT(E19,H19,K19)=0,0,MIN(IF(E19>0,E19,1E+99),IF(H19>0,H19,1E+99),IF(K19>0,K19,1E+99))),D19,IF(H19=IF(COUNT(E19,H19,K19)=0,0,MIN(IF(E19>0,E19,1E+99),IF(H19>0,H19,1E+99),IF(K19>0,K19,1E+99))),G19,J19)))))),0) -> 0
A20: 1 | B20: Foundation & Slab | C20: ='Scope & Phases'!D20 -> 0 | N20: =IFERROR(IF($C20<>"x",0,IF($M20=1,E20,IF($M20=2,H20,IF($M20=3,K20,IF(COUNT(E20,H20,K20)=0,0,MIN(IF(E20>0,E20,1E+99),IF(H20>0,H20,1E+99),IF(K20>0,K20,1E+99))))))),0) -> 0 | O20: =IFERROR(IF($C20<>"x",0,IF($M20=1,F20,IF($M20=2,I20,IF($M20=3,L20,IF(E20=IF(COUNT(E20,H20,K20)=0,0,MIN(IF(E20>0,E20,1E+99),IF(H20>0,H20,1E+99),IF(K20>0,K20,1E+99))),F20,IF(H20=IF(COUNT(E20,H20,K20)=0,0,MIN(IF(E20>0,E20,1E+99),IF(H20>0,H20,1E+99),IF(K20>0,K20,1E+99))),I20,L20)))))),0) -> 0 | P20: =IFERROR(IF($C20<>"x",0,IF($M20=1,D20,IF($M20=2,G20,IF($M20=3,J20,IF(E20=IF(COUNT(E20,H20,K20)=0,0,MIN(IF(E20>0,E20,1E+99),IF(H20>0,H20,1E+99),IF(K20>0,K20,1E+99))),D20,IF(H20=IF(COUNT(E20,H20,K20)=0,0,MIN(IF(E20>0,E20,1E+99),IF(H20>0,H20,1E+99),IF(K20>0,K20,1E+99))),G20,J20)))))),0) -> 0
A21: 1 | B21: Underground Plumbing | C21: ='Scope & Phases'!D21 -> 0 | N21: =IFERROR(IF($C21<>"x",0,IF($M21=1,E21,IF($M21=2,H21,IF($M21=3,K21,IF(COUNT(E21,H21,K21)=0,0,MIN(IF(E21>0,E21,1E+99),IF(H21>0,H21,1E+99),IF(K21>0,K21,1E+99))))))),0) -> 0 | O21: =IFERROR(IF($C21<>"x",0,IF($M21=1,F21,IF($M21=2,I21,IF($M21=3,L21,IF(E21=IF(COUNT(E21,H21,K21)=0,0,MIN(IF(E21>0,E21,1E+99),IF(H21>0,H21,1E+99),IF(K21>0,K21,1E+99))),F21,IF(H21=IF(COUNT(E21,H21,K21)=0,0,MIN(IF(E21>0,E21,1E+99),IF(H21>0,H21,1E+99),IF(K21>0,K21,1E+99))),I21,L21)))))),0) -> 0 | P21: =IFERROR(IF($C21<>"x",0,IF($M21=1,D21,IF($M21=2,G21,IF($M21=3,J21,IF(E21=IF(COUNT(E21,H21,K21)=0,0,MIN(IF(E21>0,E21,1E+99),IF(H21>0,H21,1E+99),IF(K21>0,K21,1E+99))),D21,IF(H21=IF(COUNT(E21,H21,K21)=0,0,MIN(IF(E21>0,E21,1E+99),IF(H21>0,H21,1E+99),IF(K21>0,K21,1E+99))),G21,J21)))))),0) -> 0
A22: 1 | B22: Septic | C22: ='Scope & Phases'!D22 -> 0 | N22: =IFERROR(IF($C22<>"x",0,IF($M22=1,E22,IF($M22=2,H22,IF($M22=3,K22,IF(COUNT(E22,H22,K22)=0,0,MIN(IF(E22>0,E22,1E+99),IF(H22>0,H22,1E+99),IF(K22>0,K22,1E+99))))))),0) -> 0 | O22: =IFERROR(IF($C22<>"x",0,IF($M22=1,F22,IF($M22=2,I22,IF($M22=3,L22,IF(E22=IF(COUNT(E22,H22,K22)=0,0,MIN(IF(E22>0,E22,1E+99),IF(H22>0,H22,1E+99),IF(K22>0,K22,1E+99))),F22,IF(H22=IF(COUNT(E22,H22,K22)=0,0,MIN(IF(E22>0,E22,1E+99),IF(H22>0,H22,1E+99),IF(K22>0,K22,1E+99))),I22,L22)))))),0) -> 0 | P22: =IFERROR(IF($C22<>"x",0,IF($M22=1,D22,IF($M22=2,G22,IF($M22=3,J22,IF(E22=IF(COUNT(E22,H22,K22)=0,0,MIN(IF(E22>0,E22,1E+99),IF(H22>0,H22,1E+99),IF(K22>0,K22,1E+99))),D22,IF(H22=IF(COUNT(E22,H22,K22)=0,0,MIN(IF(E22>0,E22,1E+99),IF(H22>0,H22,1E+99),IF(K22>0,K22,1E+99))),G22,J22)))))),0) -> 0
A23: 1 | B23: Underground Electrical & Service | C23: ='Scope & Phases'!D23 -> 0 | N23: =IFERROR(IF($C23<>"x",0,IF($M23=1,E23,IF($M23=2,H23,IF($M23=3,K23,IF(COUNT(E23,H23,K23)=0,0,MIN(IF(E23>0,E23,1E+99),IF(H23>0,H23,1E+99),IF(K23>0,K23,1E+99))))))),0) -> 0 | O23: =IFERROR(IF($C23<>"x",0,IF($M23=1,F23,IF($M23=2,I23,IF($M23=3,L23,IF(E23=IF(COUNT(E23,H23,K23)=0,0,MIN(IF(E23>0,E23,1E+99),IF(H23>0,H23,1E+99),IF(K23>0,K23,1E+99))),F23,IF(H23=IF(COUNT(E23,H23,K23)=0,0,MIN(IF(E23>0,E23,1E+99),IF(H23>0,H23,1E+99),IF(K23>0,K23,1E+99))),I23,L23)))))),0) -> 0 | P23: =IFERROR(IF($C23<>"x",0,IF($M23=1,D23,IF($M23=2,G23,IF($M23=3,J23,IF(E23=IF(COUNT(E23,H23,K23)=0,0,MIN(IF(E23>0,E23,1E+99),IF(H23>0,H23,1E+99),IF(K23>0,K23,1E+99))),D23,IF(H23=IF(COUNT(E23,H23,K23)=0,0,MIN(IF(E23>0,E23,1E+99),IF(H23>0,H23,1E+99),IF(K23>0,K23,1E+99))),G23,J23)))))),0) -> 0
A24: 1 | B24: Pest & Soil Treatment | C24: ='Scope & Phases'!D24 -> x | E24: 450 | F24: 1 | N24: =IFERROR(IF($C24<>"x",0,IF($M24=1,E24,IF($M24=2,H24,IF($M24=3,K24,IF(COUNT(E24,H24,K24)=0,0,MIN(IF(E24>0,E24,1E+99),IF(H24>0,H24,1E+99),IF(K24>0,K24,1E+99))))))),0) -> 450 | O24: =IFERROR(IF($C24<>"x",0,IF($M24=1,F24,IF($M24=2,I24,IF($M24=3,L24,IF(E24=IF(COUNT(E24,H24,K24)=0,0,MIN(IF(E24>0,E24,1E+99),IF(H24>0,H24,1E+99),IF(K24>0,K24,1E+99))),F24,IF(H24=IF(COUNT(E24,H24,K24)=0,0,MIN(IF(E24>0,E24,1E+99),IF(H24>0,H24,1E+99),IF(K24>0,K24,1E+99))),I24,L24)))))),0) -> 1 | P24: =IFERROR(IF($C24<>"x",0,IF($M24=1,D24,IF($M24=2,G24,IF($M24=3,J24,IF(E24=IF(COUNT(E24,H24,K24)=0,0,MIN(IF(E24>0,E24,1E+99),IF(H24>0,H24,1E+99),IF(K24>0,K24,1E+99))),D24,IF(H24=IF(COUNT(E24,H24,K24)=0,0,MIN(IF(E24>0,E24,1E+99),IF(H24>0,H24,1E+99),IF(K24>0,K24,1E+99))),G24,J24)))))),0) -> 0
A25: 2 | B25: Framing Labor | C25: ='Scope & Phases'!D25 -> x | D25: Framing Done Right LLC | E25: 3350 | F25: 6 | N25: =IFERROR(IF($C25<>"x",0,IF($M25=1,E25,IF($M25=2,H25,IF($M25=3,K25,IF(COUNT(E25,H25,K25)=0,0,MIN(IF(E25>0,E25,1E+99),IF(H25>0,H25,1E+99),IF(K25>0,K25,1E+99))))))),0) -> 3350 | O25: =IFERROR(IF($C25<>"x",0,IF($M25=1,F25,IF($M25=2,I25,IF($M25=3,L25,IF(E25=IF(COUNT(E25,H25,K25)=0,0,MIN(IF(E25>0,E25,1E+99),IF(H25>0,H25,1E+99),IF(K25>0,K25,1E+99))),F25,IF(H25=IF(COUNT(E25,H25,K25)=0,0,MIN(IF(E25>0,E25,1E+99),IF(H25>0,H25,1E+99),IF(K25>0,K25,1E+99))),I25,L25)))))),0) -> 6 | P25: =IFERROR(IF($C25<>"x",0,IF($M25=1,D25,IF($M25=2,G25,IF($M25=3,J25,IF(E25=IF(COUNT(E25,H25,K25)=0,0,MIN(IF(E25>0,E25,1E+99),IF(H25>0,H25,1E+99),IF(K25>0,K25,1E+99))),D25,IF(H25=IF(COUNT(E25,H25,K25)=0,0,MIN(IF(E25>0,E25,1E+99),IF(H25>0,H25,1E+99),IF(K25>0,K25,1E+99))),G25,J25)))))),0) -> Framing Done Right LLC
A26: 2 | B26: Framing Material | C26: ='Scope & Phases'!D26 -> x | D26: 84 Lumber | E26: 2725 | F26: 2 | N26: =IFERROR(IF($C26<>"x",0,IF($M26=1,E26,IF($M26=2,H26,IF($M26=3,K26,IF(COUNT(E26,H26,K26)=0,0,MIN(IF(E26>0,E26,1E+99),IF(H26>0,H26,1E+99),IF(K26>0,K26,1E+99))))))),0) -> 2725 | O26: =IFERROR(IF($C26<>"x",0,IF($M26=1,F26,IF($M26=2,I26,IF($M26=3,L26,IF(E26=IF(COUNT(E26,H26,K26)=0,0,MIN(IF(E26>0,E26,1E+99),IF(H26>0,H26,1E+99),IF(K26>0,K26,1E+99))),F26,IF(H26=IF(COUNT(E26,H26,K26)=0,0,MIN(IF(E26>0,E26,1E+99),IF(H26>0,H26,1E+99),IF(K26>0,K26,1E+99))),I26,L26)))))),0) -> 2 | P26: =IFERROR(IF($C26<>"x",0,IF($M26=1,D26,IF($M26=2,G26,IF($M26=3,J26,IF(E26=IF(COUNT(E26,H26,K26)=0,0,MIN(IF(E26>0,E26,1E+99),IF(H26>0,H26,1E+99),IF(K26>0,K26,1E+99))),D26,IF(H26=IF(COUNT(E26,H26,K26)=0,0,MIN(IF(E26>0,E26,1E+99),IF(H26>0,H26,1E+99),IF(K26>0,K26,1E+99))),G26,J26)))))),0) -> 84 Lumber
A27: 2 | B27: Structural Steel & Beams | C27: ='Scope & Phases'!D27 -> 0 | N27: =IFERROR(IF($C27<>"x",0,IF($M27=1,E27,IF($M27=2,H27,IF($M27=3,K27,IF(COUNT(E27,H27,K27)=0,0,MIN(IF(E27>0,E27,1E+99),IF(H27>0,H27,1E+99),IF(K27>0,K27,1E+99))))))),0) -> 0 | O27: =IFERROR(IF($C27<>"x",0,IF($M27=1,F27,IF($M27=2,I27,IF($M27=3,L27,IF(E27=IF(COUNT(E27,H27,K27)=0,0,MIN(IF(E27>0,E27,1E+99),IF(H27>0,H27,1E+99),IF(K27>0,K27,1E+99))),F27,IF(H27=IF(COUNT(E27,H27,K27)=0,0,MIN(IF(E27>0,E27,1E+99),IF(H27>0,H27,1E+99),IF(K27>0,K27,1E+99))),I27,L27)))))),0) -> 0 | P27: =IFERROR(IF($C27<>"x",0,IF($M27=1,D27,IF($M27=2,G27,IF($M27=3,J27,IF(E27=IF(COUNT(E27,H27,K27)=0,0,MIN(IF(E27>0,E27,1E+99),IF(H27>0,H27,1E+99),IF(K27>0,K27,1E+99))),D27,IF(H27=IF(COUNT(E27,H27,K27)=0,0,MIN(IF(E27>0,E27,1E+99),IF(H27>0,H27,1E+99),IF(K27>0,K27,1E+99))),G27,J27)))))),0) -> 0
A28: 2 | B28: Roofing | C28: ='Scope & Phases'!D28 -> x | D28: Sun Valley Roofing | E28: 6950 | F28: 4 | G28: Desert Ridge Roofing | H28: 7925 | I28: 5 | J28: AZ Peak Roofing | K28: 7375 | L28: 3 | N28: =IFERROR(IF($C28<>"x",0,IF($M28=1,E28,IF($M28=2,H28,IF($M28=3,K28,IF(COUNT(E28,H28,K28)=0,0,MIN(IF(E28>0,E28,1E+99),IF(H28>0,H28,1E+99),IF(K28>0,K28,1E+99))))))),0) -> 6950 | O28: =IFERROR(IF($C28<>"x",0,IF($M28=1,F28,IF($M28=2,I28,IF($M28=3,L28,IF(E28=IF(COUNT(E28,H28,K28)=0,0,MIN(IF(E28>0,E28,1E+99),IF(H28>0,H28,1E+99),IF(K28>0,K28,1E+99))),F28,IF(H28=IF(COUNT(E28,H28,K28)=0,0,MIN(IF(E28>0,E28,1E+99),IF(H28>0,H28,1E+99),IF(K28>0,K28,1E+99))),I28,L28)))))),0) -> 4 | P28: =IFERROR(IF($C28<>"x",0,IF($M28=1,D28,IF($M28=2,G28,IF($M28=3,J28,IF(E28=IF(COUNT(E28,H28,K28)=0,0,MIN(IF(E28>0,E28,1E+99),IF(H28>0,H28,1E+99),IF(K28>0,K28,1E+99))),D28,IF(H28=IF(COUNT(E28,H28,K28)=0,0,MIN(IF(E28>0,E28,1E+99),IF(H28>0,H28,1E+99),IF(K28>0,K28,1E+99))),G28,J28)))))),0) -> Sun Valley Roofing
A29: 2 | B29: Windows & Exterior Doors | C29: ='Scope & Phases'!D29 -> x | D29: Arcadia Glass Co | E29: 5450 | F29: 3 | N29: =IFERROR(IF($C29<>"x",0,IF($M29=1,E29,IF($M29=2,H29,IF($M29=3,K29,IF(COUNT(E29,H29,K29)=0,0,MIN(IF(E29>0,E29,1E+99),IF(H29>0,H29,1E+99),IF(K29>0,K29,1E+99))))))),0) -> 5450 | O29: =IFERROR(IF($C29<>"x",0,IF($M29=1,F29,IF($M29=2,I29,IF($M29=3,L29,IF(E29=IF(COUNT(E29,H29,K29)=0,0,MIN(IF(E29>0,E29,1E+99),IF(H29>0,H29,1E+99),IF(K29>0,K29,1E+99))),F29,IF(H29=IF(COUNT(E29,H29,K29)=0,0,MIN(IF(E29>0,E29,1E+99),IF(H29>0,H29,1E+99),IF(K29>0,K29,1E+99))),I29,L29)))))),0) -> 3 | P29: =IFERROR(IF($C29<>"x",0,IF($M29=1,D29,IF($M29=2,G29,IF($M29=3,J29,IF(E29=IF(COUNT(E29,H29,K29)=0,0,MIN(IF(E29>0,E29,1E+99),IF(H29>0,H29,1E+99),IF(K29>0,K29,1E+99))),D29,IF(H29=IF(COUNT(E29,H29,K29)=0,0,MIN(IF(E29>0,E29,1E+99),IF(H29>0,H29,1E+99),IF(K29>0,K29,1E+99))),G29,J29)))))),0) -> Arcadia Glass Co
A30: 2 | B30: Rough Plumbing | C30: ='Scope & Phases'!D30 -> x | D30: Copperline Plumbing | E30: 3875 | F30: 5 | N30: =IFERROR(IF($C30<>"x",0,IF($M30=1,E30,IF($M30=2,H30,IF($M30=3,K30,IF(COUNT(E30,H30,K30)=0,0,MIN(IF(E30>0,E30,1E+99),IF(H30>0,H30,1E+99),IF(K30>0,K30,1E+99))))))),0) -> 3875 | O30: =IFERROR(IF($C30<>"x",0,IF($M30=1,F30,IF($M30=2,I30,IF($M30=3,L30,IF(E30=IF(COUNT(E30,H30,K30)=0,0,MIN(IF(E30>0,E30,1E+99),IF(H30>0,H30,1E+99),IF(K30>0,K30,1E+99))),F30,IF(H30=IF(COUNT(E30,H30,K30)=0,0,MIN(IF(E30>0,E30,1E+99),IF(H30>0,H30,1E+99),IF(K30>0,K30,1E+99))),I30,L30)))))),0) -> 5 | P30: =IFERROR(IF($C30<>"x",0,IF($M30=1,D30,IF($M30=2,G30,IF($M30=3,J30,IF(E30=IF(COUNT(E30,H30,K30)=0,0,MIN(IF(E30>0,E30,1E+99),IF(H30>0,H30,1E+99),IF(K30>0,K30,1E+99))),D30,IF(H30=IF(COUNT(E30,H30,K30)=0,0,MIN(IF(E30>0,E30,1E+99),IF(H30>0,H30,1E+99),IF(K30>0,K30,1E+99))),G30,J30)))))),0) -> Copperline Plumbing
A31: 2 | B31: Rough Electrical | C31: ='Scope & Phases'!D31 -> x | D31: Voltz Electric | E31: 4300 | F31: 6 | G31: Mesa Sparks LLC | H31: 4900 | I31: 7 | J31: Rincon Electrical | K31: 4550 | L31: 5 | N31: =IFERROR(IF($C31<>"x",0,IF($M31=1,E31,IF($M31=2,H31,IF($M31=3,K31,IF(COUNT(E31,H31,K31)=0,0,MIN(IF(E31>0,E31,1E+99),IF(H31>0,H31,1E+99),IF(K31>0,K31,1E+99))))))),0) -> 4300 | O31: =IFERROR(IF($C31<>"x",0,IF($M31=1,F31,IF($M31=2,I31,IF($M31=3,L31,IF(E31=IF(COUNT(E31,H31,K31)=0,0,MIN(IF(E31>0,E31,1E+99),IF(H31>0,H31,1E+99),IF(K31>0,K31,1E+99))),F31,IF(H31=IF(COUNT(E31,H31,K31)=0,0,MIN(IF(E31>0,E31,1E+99),IF(H31>0,H31,1E+99),IF(K31>0,K31,1E+99))),I31,L31)))))),0) -> 6 | P31: =IFERROR(IF($C31<>"x",0,IF($M31=1,D31,IF($M31=2,G31,IF($M31=3,J31,IF(E31=IF(COUNT(E31,H31,K31)=0,0,MIN(IF(E31>0,E31,1E+99),IF(H31>0,H31,1E+99),IF(K31>0,K31,1E+99))),D31,IF(H31=IF(COUNT(E31,H31,K31)=0,0,MIN(IF(E31>0,E31,1E+99),IF(H31>0,H31,1E+99),IF(K31>0,K31,1E+99))),G31,J31)))))),0) -> Voltz Electric
A32: 2 | B32: Rough HVAC | C32: ='Scope & Phases'!D32 -> x | D32: Sonoran Air | E32: 5975 | F32: 4 | N32: =IFERROR(IF($C32<>"x",0,IF($M32=1,E32,IF($M32=2,H32,IF($M32=3,K32,IF(COUNT(E32,H32,K32)=0,0,MIN(IF(E32>0,E32,1E+99),IF(H32>0,H32,1E+99),IF(K32>0,K32,1E+99))))))),0) -> 5975 | O32: =IFERROR(IF($C32<>"x",0,IF($M32=1,F32,IF($M32=2,I32,IF($M32=3,L32,IF(E32=IF(COUNT(E32,H32,K32)=0,0,MIN(IF(E32>0,E32,1E+99),IF(H32>0,H32,1E+99),IF(K32>0,K32,1E+99))),F32,IF(H32=IF(COUNT(E32,H32,K32)=0,0,MIN(IF(E32>0,E32,1E+99),IF(H32>0,H32,1E+99),IF(K32>0,K32,1E+99))),I32,L32)))))),0) -> 4 | P32: =IFERROR(IF($C32<>"x",0,IF($M32=1,D32,IF($M32=2,G32,IF($M32=3,J32,IF(E32=IF(COUNT(E32,H32,K32)=0,0,MIN(IF(E32>0,E32,1E+99),IF(H32>0,H32,1E+99),IF(K32>0,K32,1E+99))),D32,IF(H32=IF(COUNT(E32,H32,K32)=0,0,MIN(IF(E32>0,E32,1E+99),IF(H32>0,H32,1E+99),IF(K32>0,K32,1E+99))),G32,J32)))))),0) -> Sonoran Air
A33: 2 | B33: Low Voltage Rough | C33: ='Scope & Phases'!D33 -> 0 | N33: =IFERROR(IF($C33<>"x",0,IF($M33=1,E33,IF($M33=2,H33,IF($M33=3,K33,IF(COUNT(E33,H33,K33)=0,0,MIN(IF(E33>0,E33,1E+99),IF(H33>0,H33,1E+99),IF(K33>0,K33,1E+99))))))),0) -> 0 | O33: =IFERROR(IF($C33<>"x",0,IF($M33=1,F33,IF($M33=2,I33,IF($M33=3,L33,IF(E33=IF(COUNT(E33,H33,K33)=0,0,MIN(IF(E33>0,E33,1E+99),IF(H33>0,H33,1E+99),IF(K33>0,K33,1E+99))),F33,IF(H33=IF(COUNT(E33,H33,K33)=0,0,MIN(IF(E33>0,E33,1E+99),IF(H33>0,H33,1E+99),IF(K33>0,K33,1E+99))),I33,L33)))))),0) -> 0 | P33: =IFERROR(IF($C33<>"x",0,IF($M33=1,D33,IF($M33=2,G33,IF($M33=3,J33,IF(E33=IF(COUNT(E33,H33,K33)=0,0,MIN(IF(E33>0,E33,1E+99),IF(H33>0,H33,1E+99),IF(K33>0,K33,1E+99))),D33,IF(H33=IF(COUNT(E33,H33,K33)=0,0,MIN(IF(E33>0,E33,1E+99),IF(H33>0,H33,1E+99),IF(K33>0,K33,1E+99))),G33,J33)))))),0) -> 0
A34: 2 | B34: Rough Inspections | C34: ='Scope & Phases'!D34 -> x | E34: 300 | F34: 3 | N34: =IFERROR(IF($C34<>"x",0,IF($M34=1,E34,IF($M34=2,H34,IF($M34=3,K34,IF(COUNT(E34,H34,K34)=0,0,MIN(IF(E34>0,E34,1E+99),IF(H34>0,H34,1E+99),IF(K34>0,K34,1E+99))))))),0) -> 300 | O34: =IFERROR(IF($C34<>"x",0,IF($M34=1,F34,IF($M34=2,I34,IF($M34=3,L34,IF(E34=IF(COUNT(E34,H34,K34)=0,0,MIN(IF(E34>0,E34,1E+99),IF(H34>0,H34,1E+99),IF(K34>0,K34,1E+99))),F34,IF(H34=IF(COUNT(E34,H34,K34)=0,0,MIN(IF(E34>0,E34,1E+99),IF(H34>0,H34,1E+99),IF(K34>0,K34,1E+99))),I34,L34)))))),0) -> 3 | P34: =IFERROR(IF($C34<>"x",0,IF($M34=1,D34,IF($M34=2,G34,IF($M34=3,J34,IF(E34=IF(COUNT(E34,H34,K34)=0,0,MIN(IF(E34>0,E34,1E+99),IF(H34>0,H34,1E+99),IF(K34>0,K34,1E+99))),D34,IF(H34=IF(COUNT(E34,H34,K34)=0,0,MIN(IF(E34>0,E34,1E+99),IF(H34>0,H34,1E+99),IF(K34>0,K34,1E+99))),G34,J34)))))),0) -> 0
A35: 3 | B35: Insulation | C35: ='Scope & Phases'!D35 -> x | D35: Valley Insulation | E35: 1850 | F35: 2 | N35: =IFERROR(IF($C35<>"x",0,IF($M35=1,E35,IF($M35=2,H35,IF($M35=3,K35,IF(COUNT(E35,H35,K35)=0,0,MIN(IF(E35>0,E35,1E+99),IF(H35>0,H35,1E+99),IF(K35>0,K35,1E+99))))))),0) -> 1850 | O35: =IFERROR(IF($C35<>"x",0,IF($M35=1,F35,IF($M35=2,I35,IF($M35=3,L35,IF(E35=IF(COUNT(E35,H35,K35)=0,0,MIN(IF(E35>0,E35,1E+99),IF(H35>0,H35,1E+99),IF(K35>0,K35,1E+99))),F35,IF(H35=IF(COUNT(E35,H35,K35)=0,0,MIN(IF(E35>0,E35,1E+99),IF(H35>0,H35,1E+99),IF(K35>0,K35,1E+99))),I35,L35)))))),0) -> 2 | P35: =IFERROR(IF($C35<>"x",0,IF($M35=1,D35,IF($M35=2,G35,IF($M35=3,J35,IF(E35=IF(COUNT(E35,H35,K35)=0,0,MIN(IF(E35>0,E35,1E+99),IF(H35>0,H35,1E+99),IF(K35>0,K35,1E+99))),D35,IF(H35=IF(COUNT(E35,H35,K35)=0,0,MIN(IF(E35>0,E35,1E+99),IF(H35>0,H35,1E+99),IF(K35>0,K35,1E+99))),G35,J35)))))),0) -> Valley Insulation
A36: 3 | B36: Drywall | C36: ='Scope & Phases'!D36 -> x | D36: Level 5 Drywall | E36: 5625 | F36: 8 | G36: Smooth Wall Co | H36: 6400 | I36: 9 | J36: Canyon Drywall | K36: 5950 | L36: 7 | N36: =IFERROR(IF($C36<>"x",0,IF($M36=1,E36,IF($M36=2,H36,IF($M36=3,K36,IF(COUNT(E36,H36,K36)=0,0,MIN(IF(E36>0,E36,1E+99),IF(H36>0,H36,1E+99),IF(K36>0,K36,1E+99))))))),0) -> 5625 | O36: =IFERROR(IF($C36<>"x",0,IF($M36=1,F36,IF($M36=2,I36,IF($M36=3,L36,IF(E36=IF(COUNT(E36,H36,K36)=0,0,MIN(IF(E36>0,E36,1E+99),IF(H36>0,H36,1E+99),IF(K36>0,K36,1E+99))),F36,IF(H36=IF(COUNT(E36,H36,K36)=0,0,MIN(IF(E36>0,E36,1E+99),IF(H36>0,H36,1E+99),IF(K36>0,K36,1E+99))),I36,L36)))))),0) -> 8 | P36: =IFERROR(IF($C36<>"x",0,IF($M36=1,D36,IF($M36=2,G36,IF($M36=3,J36,IF(E36=IF(COUNT(E36,H36,K36)=0,0,MIN(IF(E36>0,E36,1E+99),IF(H36>0,H36,1E+99),IF(K36>0,K36,1E+99))),D36,IF(H36=IF(COUNT(E36,H36,K36)=0,0,MIN(IF(E36>0,E36,1E+99),IF(H36>0,H36,1E+99),IF(K36>0,K36,1E+99))),G36,J36)))))),0) -> Level 5 Drywall
A37: 3 | B37: Interior Doors | C37: ='Scope & Phases'!D37 -> x | E37: 2025 | F37: 3 | N37: =IFERROR(IF($C37<>"x",0,IF($M37=1,E37,IF($M37=2,H37,IF($M37=3,K37,IF(COUNT(E37,H37,K37)=0,0,MIN(IF(E37>0,E37,1E+99),IF(H37>0,H37,1E+99),IF(K37>0,K37,1E+99))))))),0) -> 2025 | O37: =IFERROR(IF($C37<>"x",0,IF($M37=1,F37,IF($M37=2,I37,IF($M37=3,L37,IF(E37=IF(COUNT(E37,H37,K37)=0,0,MIN(IF(E37>0,E37,1E+99),IF(H37>0,H37,1E+99),IF(K37>0,K37,1E+99))),F37,IF(H37=IF(COUNT(E37,H37,K37)=0,0,MIN(IF(E37>0,E37,1E+99),IF(H37>0,H37,1E+99),IF(K37>0,K37,1E+99))),I37,L37)))))),0) -> 3 | P37: =IFERROR(IF($C37<>"x",0,IF($M37=1,D37,IF($M37=2,G37,IF($M37=3,J37,IF(E37=IF(COUNT(E37,H37,K37)=0,0,MIN(IF(E37>0,E37,1E+99),IF(H37>0,H37,1E+99),IF(K37>0,K37,1E+99))),D37,IF(H37=IF(COUNT(E37,H37,K37)=0,0,MIN(IF(E37>0,E37,1E+99),IF(H37>0,H37,1E+99),IF(K37>0,K37,1E+99))),G37,J37)))))),0) -> 0
A38: 3 | B38: Trim & Millwork | C38: ='Scope & Phases'!D38 -> x | E38: 2550 | F38: 4 | N38: =IFERROR(IF($C38<>"x",0,IF($M38=1,E38,IF($M38=2,H38,IF($M38=3,K38,IF(COUNT(E38,H38,K38)=0,0,MIN(IF(E38>0,E38,1E+99),IF(H38>0,H38,1E+99),IF(K38>0,K38,1E+99))))))),0) -> 2550 | O38: =IFERROR(IF($C38<>"x",0,IF($M38=1,F38,IF($M38=2,I38,IF($M38=3,L38,IF(E38=IF(COUNT(E38,H38,K38)=0,0,MIN(IF(E38>0,E38,1E+99),IF(H38>0,H38,1E+99),IF(K38>0,K38,1E+99))),F38,IF(H38=IF(COUNT(E38,H38,K38)=0,0,MIN(IF(E38>0,E38,1E+99),IF(H38>0,H38,1E+99),IF(K38>0,K38,1E+99))),I38,L38)))))),0) -> 4 | P38: =IFERROR(IF($C38<>"x",0,IF($M38=1,D38,IF($M38=2,G38,IF($M38=3,J38,IF(E38=IF(COUNT(E38,H38,K38)=0,0,MIN(IF(E38>0,E38,1E+99),IF(H38>0,H38,1E+99),IF(K38>0,K38,1E+99))),D38,IF(H38=IF(COUNT(E38,H38,K38)=0,0,MIN(IF(E38>0,E38,1E+99),IF(H38>0,H38,1E+99),IF(K38>0,K38,1E+99))),G38,J38)))))),0) -> 0
A39: 3 | B39: Stairs & Railings | C39: ='Scope & Phases'!D39 -> 0 | N39: =IFERROR(IF($C39<>"x",0,IF($M39=1,E39,IF($M39=2,H39,IF($M39=3,K39,IF(COUNT(E39,H39,K39)=0,0,MIN(IF(E39>0,E39,1E+99),IF(H39>0,H39,1E+99),IF(K39>0,K39,1E+99))))))),0) -> 0 | O39: =IFERROR(IF($C39<>"x",0,IF($M39=1,F39,IF($M39=2,I39,IF($M39=3,L39,IF(E39=IF(COUNT(E39,H39,K39)=0,0,MIN(IF(E39>0,E39,1E+99),IF(H39>0,H39,1E+99),IF(K39>0,K39,1E+99))),F39,IF(H39=IF(COUNT(E39,H39,K39)=0,0,MIN(IF(E39>0,E39,1E+99),IF(H39>0,H39,1E+99),IF(K39>0,K39,1E+99))),I39,L39)))))),0) -> 0 | P39: =IFERROR(IF($C39<>"x",0,IF($M39=1,D39,IF($M39=2,G39,IF($M39=3,J39,IF(E39=IF(COUNT(E39,H39,K39)=0,0,MIN(IF(E39>0,E39,1E+99),IF(H39>0,H39,1E+99),IF(K39>0,K39,1E+99))),D39,IF(H39=IF(COUNT(E39,H39,K39)=0,0,MIN(IF(E39>0,E39,1E+99),IF(H39>0,H39,1E+99),IF(K39>0,K39,1E+99))),G39,J39)))))),0) -> 0
A40: 3 | B40: Interior Paint | C40: ='Scope & Phases'!D40 -> x | D40: Brushworks AZ | E40: 4050 | F40: 5 | N40: =IFERROR(IF($C40<>"x",0,IF($M40=1,E40,IF($M40=2,H40,IF($M40=3,K40,IF(COUNT(E40,H40,K40)=0,0,MIN(IF(E40>0,E40,1E+99),IF(H40>0,H40,1E+99),IF(K40>0,K40,1E+99))))))),0) -> 4050 | O40: =IFERROR(IF($C40<>"x",0,IF($M40=1,F40,IF($M40=2,I40,IF($M40=3,L40,IF(E40=IF(COUNT(E40,H40,K40)=0,0,MIN(IF(E40>0,E40,1E+99),IF(H40>0,H40,1E+99),IF(K40>0,K40,1E+99))),F40,IF(H40=IF(COUNT(E40,H40,K40)=0,0,MIN(IF(E40>0,E40,1E+99),IF(H40>0,H40,1E+99),IF(K40>0,K40,1E+99))),I40,L40)))))),0) -> 5 | P40: =IFERROR(IF($C40<>"x",0,IF($M40=1,D40,IF($M40=2,G40,IF($M40=3,J40,IF(E40=IF(COUNT(E40,H40,K40)=0,0,MIN(IF(E40>0,E40,1E+99),IF(H40>0,H40,1E+99),IF(K40>0,K40,1E+99))),D40,IF(H40=IF(COUNT(E40,H40,K40)=0,0,MIN(IF(E40>0,E40,1E+99),IF(H40>0,H40,1E+99),IF(K40>0,K40,1E+99))),G40,J40)))))),0) -> Brushworks AZ
A41: 4 | B41: Kitchen Cabinets | C41: ='Scope & Phases'!D41 -> x | D41: Copper State Cabinets | E41: 6075 | F41: 4 | G41: Mesa Cabinet Works | H41: 6925 | I41: 5 | J41: Sundance Millwork | K41: 6450 | L41: 3 | N41: =IFERROR(IF($C41<>"x",0,IF($M41=1,E41,IF($M41=2,H41,IF($M41=3,K41,IF(COUNT(E41,H41,K41)=0,0,MIN(IF(E41>0,E41,1E+99),IF(H41>0,H41,1E+99),IF(K41>0,K41,1E+99))))))),0) -> 6075 | O41: =IFERROR(IF($C41<>"x",0,IF($M41=1,F41,IF($M41=2,I41,IF($M41=3,L41,IF(E41=IF(COUNT(E41,H41,K41)=0,0,MIN(IF(E41>0,E41,1E+99),IF(H41>0,H41,1E+99),IF(K41>0,K41,1E+99))),F41,IF(H41=IF(COUNT(E41,H41,K41)=0,0,MIN(IF(E41>0,E41,1E+99),IF(H41>0,H41,1E+99),IF(K41>0,K41,1E+99))),I41,L41)))))),0) -> 4 | P41: =IFERROR(IF($C41<>"x",0,IF($M41=1,D41,IF($M41=2,G41,IF($M41=3,J41,IF(E41=IF(COUNT(E41,H41,K41)=0,0,MIN(IF(E41>0,E41,1E+99),IF(H41>0,H41,1E+99),IF(K41>0,K41,1E+99))),D41,IF(H41=IF(COUNT(E41,H41,K41)=0,0,MIN(IF(E41>0,E41,1E+99),IF(H41>0,H41,1E+99),IF(K41>0,K41,1E+99))),G41,J41)))))),0) -> Copper State Cabinets
A42: 4 | B42: Bath Vanities | C42: ='Scope & Phases'!D42 -> x | E42: 1625 | F42: 2 | N42: =IFERROR(IF($C42<>"x",0,IF($M42=1,E42,IF($M42=2,H42,IF($M42=3,K42,IF(COUNT(E42,H42,K42)=0,0,MIN(IF(E42>0,E42,1E+99),IF(H42>0,H42,1E+99),IF(K42>0,K42,1E+99))))))),0) -> 1625 | O42: =IFERROR(IF($C42<>"x",0,IF($M42=1,F42,IF($M42=2,I42,IF($M42=3,L42,IF(E42=IF(COUNT(E42,H42,K42)=0,0,MIN(IF(E42>0,E42,1E+99),IF(H42>0,H42,1E+99),IF(K42>0,K42,1E+99))),F42,IF(H42=IF(COUNT(E42,H42,K42)=0,0,MIN(IF(E42>0,E42,1E+99),IF(H42>0,H42,1E+99),IF(K42>0,K42,1E+99))),I42,L42)))))),0) -> 2 | P42: =IFERROR(IF($C42<>"x",0,IF($M42=1,D42,IF($M42=2,G42,IF($M42=3,J42,IF(E42=IF(COUNT(E42,H42,K42)=0,0,MIN(IF(E42>0,E42,1E+99),IF(H42>0,H42,1E+99),IF(K42>0,K42,1E+99))),D42,IF(H42=IF(COUNT(E42,H42,K42)=0,0,MIN(IF(E42>0,E42,1E+99),IF(H42>0,H42,1E+99),IF(K42>0,K42,1E+99))),G42,J42)))))),0) -> 0
A43: 4 | B43: Laundry & Utility Cabinets | C43: ='Scope & Phases'!D43 -> x | E43: 675 | F43: 1 | N43: =IFERROR(IF($C43<>"x",0,IF($M43=1,E43,IF($M43=2,H43,IF($M43=3,K43,IF(COUNT(E43,H43,K43)=0,0,MIN(IF(E43>0,E43,1E+99),IF(H43>0,H43,1E+99),IF(K43>0,K43,1E+99))))))),0) -> 675 | O43: =IFERROR(IF($C43<>"x",0,IF($M43=1,F43,IF($M43=2,I43,IF($M43=3,L43,IF(E43=IF(COUNT(E43,H43,K43)=0,0,MIN(IF(E43>0,E43,1E+99),IF(H43>0,H43,1E+99),IF(K43>0,K43,1E+99))),F43,IF(H43=IF(COUNT(E43,H43,K43)=0,0,MIN(IF(E43>0,E43,1E+99),IF(H43>0,H43,1E+99),IF(K43>0,K43,1E+99))),I43,L43)))))),0) -> 1 | P43: =IFERROR(IF($C43<>"x",0,IF($M43=1,D43,IF($M43=2,G43,IF($M43=3,J43,IF(E43=IF(COUNT(E43,H43,K43)=0,0,MIN(IF(E43>0,E43,1E+99),IF(H43>0,H43,1E+99),IF(K43>0,K43,1E+99))),D43,IF(H43=IF(COUNT(E43,H43,K43)=0,0,MIN(IF(E43>0,E43,1E+99),IF(H43>0,H43,1E+99),IF(K43>0,K43,1E+99))),G43,J43)))))),0) -> 0
A44: 4 | B44: Closet Systems | C44: ='Scope & Phases'!D44 -> 0 | N44: =IFERROR(IF($C44<>"x",0,IF($M44=1,E44,IF($M44=2,H44,IF($M44=3,K44,IF(COUNT(E44,H44,K44)=0,0,MIN(IF(E44>0,E44,1E+99),IF(H44>0,H44,1E+99),IF(K44>0,K44,1E+99))))))),0) -> 0 | O44: =IFERROR(IF($C44<>"x",0,IF($M44=1,F44,IF($M44=2,I44,IF($M44=3,L44,IF(E44=IF(COUNT(E44,H44,K44)=0,0,MIN(IF(E44>0,E44,1E+99),IF(H44>0,H44,1E+99),IF(K44>0,K44,1E+99))),F44,IF(H44=IF(COUNT(E44,H44,K44)=0,0,MIN(IF(E44>0,E44,1E+99),IF(H44>0,H44,1E+99),IF(K44>0,K44,1E+99))),I44,L44)))))),0) -> 0 | P44: =IFERROR(IF($C44<>"x",0,IF($M44=1,D44,IF($M44=2,G44,IF($M44=3,J44,IF(E44=IF(COUNT(E44,H44,K44)=0,0,MIN(IF(E44>0,E44,1E+99),IF(H44>0,H44,1E+99),IF(K44>0,K44,1E+99))),D44,IF(H44=IF(COUNT(E44,H44,K44)=0,0,MIN(IF(E44>0,E44,1E+99),IF(H44>0,H44,1E+99),IF(K44>0,K44,1E+99))),G44,J44)))))),0) -> 0
A45: 4 | B45: Countertops | C45: ='Scope & Phases'!D45 -> x | D45: Stone Age Surfaces | E45: 3700 | F45: 3 | N45: =IFERROR(IF($C45<>"x",0,IF($M45=1,E45,IF($M45=2,H45,IF($M45=3,K45,IF(COUNT(E45,H45,K45)=0,0,MIN(IF(E45>0,E45,1E+99),IF(H45>0,H45,1E+99),IF(K45>0,K45,1E+99))))))),0) -> 3700 | O45: =IFERROR(IF($C45<>"x",0,IF($M45=1,F45,IF($M45=2,I45,IF($M45=3,L45,IF(E45=IF(COUNT(E45,H45,K45)=0,0,MIN(IF(E45>0,E45,1E+99),IF(H45>0,H45,1E+99),IF(K45>0,K45,1E+99))),F45,IF(H45=IF(COUNT(E45,H45,K45)=0,0,MIN(IF(E45>0,E45,1E+99),IF(H45>0,H45,1E+99),IF(K45>0,K45,1E+99))),I45,L45)))))),0) -> 3 | P45: =IFERROR(IF($C45<>"x",0,IF($M45=1,D45,IF($M45=2,G45,IF($M45=3,J45,IF(E45=IF(COUNT(E45,H45,K45)=0,0,MIN(IF(E45>0,E45,1E+99),IF(H45>0,H45,1E+99),IF(K45>0,K45,1E+99))),D45,IF(H45=IF(COUNT(E45,H45,K45)=0,0,MIN(IF(E45>0,E45,1E+99),IF(H45>0,H45,1E+99),IF(K45>0,K45,1E+99))),G45,J45)))))),0) -> Stone Age Surfaces
A46: 4 | B46: Cabinet Hardware | C46: ='Scope & Phases'!D46 -> x | E46: 550 | F46: 1 | N46: =IFERROR(IF($C46<>"x",0,IF($M46=1,E46,IF($M46=2,H46,IF($M46=3,K46,IF(COUNT(E46,H46,K46)=0,0,MIN(IF(E46>0,E46,1E+99),IF(H46>0,H46,1E+99),IF(K46>0,K46,1E+99))))))),0) -> 550 | O46: =IFERROR(IF($C46<>"x",0,IF($M46=1,F46,IF($M46=2,I46,IF($M46=3,L46,IF(E46=IF(COUNT(E46,H46,K46)=0,0,MIN(IF(E46>0,E46,1E+99),IF(H46>0,H46,1E+99),IF(K46>0,K46,1E+99))),F46,IF(H46=IF(COUNT(E46,H46,K46)=0,0,MIN(IF(E46>0,E46,1E+99),IF(H46>0,H46,1E+99),IF(K46>0,K46,1E+99))),I46,L46)))))),0) -> 1 | P46: =IFERROR(IF($C46<>"x",0,IF($M46=1,D46,IF($M46=2,G46,IF($M46=3,J46,IF(E46=IF(COUNT(E46,H46,K46)=0,0,MIN(IF(E46>0,E46,1E+99),IF(H46>0,H46,1E+99),IF(K46>0,K46,1E+99))),D46,IF(H46=IF(COUNT(E46,H46,K46)=0,0,MIN(IF(E46>0,E46,1E+99),IF(H46>0,H46,1E+99),IF(K46>0,K46,1E+99))),G46,J46)))))),0) -> 0
A47: 5 | B47: Floor Prep & Leveling | C47: ='Scope & Phases'!D47 -> x | E47: 925 | F47: 2 | N47: =IFERROR(IF($C47<>"x",0,IF($M47=1,E47,IF($M47=2,H47,IF($M47=3,K47,IF(COUNT(E47,H47,K47)=0,0,MIN(IF(E47>0,E47,1E+99),IF(H47>0,H47,1E+99),IF(K47>0,K47,1E+99))))))),0) -> 925 | O47: =IFERROR(IF($C47<>"x",0,IF($M47=1,F47,IF($M47=2,I47,IF($M47=3,L47,IF(E47=IF(COUNT(E47,H47,K47)=0,0,MIN(IF(E47>0,E47,1E+99),IF(H47>0,H47,1E+99),IF(K47>0,K47,1E+99))),F47,IF(H47=IF(COUNT(E47,H47,K47)=0,0,MIN(IF(E47>0,E47,1E+99),IF(H47>0,H47,1E+99),IF(K47>0,K47,1E+99))),I47,L47)))))),0) -> 2 | P47: =IFERROR(IF($C47<>"x",0,IF($M47=1,D47,IF($M47=2,G47,IF($M47=3,J47,IF(E47=IF(COUNT(E47,H47,K47)=0,0,MIN(IF(E47>0,E47,1E+99),IF(H47>0,H47,1E+99),IF(K47>0,K47,1E+99))),D47,IF(H47=IF(COUNT(E47,H47,K47)=0,0,MIN(IF(E47>0,E47,1E+99),IF(H47>0,H47,1E+99),IF(K47>0,K47,1E+99))),G47,J47)))))),0) -> 0
A48: 5 | B48: Floor Tile | C48: ='Scope & Phases'!D48 -> x | D48: Tile Team LLC | E48: 3000 | F48: 4 | N48: =IFERROR(IF($C48<>"x",0,IF($M48=1,E48,IF($M48=2,H48,IF($M48=3,K48,IF(COUNT(E48,H48,K48)=0,0,MIN(IF(E48>0,E48,1E+99),IF(H48>0,H48,1E+99),IF(K48>0,K48,1E+99))))))),0) -> 3000 | O48: =IFERROR(IF($C48<>"x",0,IF($M48=1,F48,IF($M48=2,I48,IF($M48=3,L48,IF(E48=IF(COUNT(E48,H48,K48)=0,0,MIN(IF(E48>0,E48,1E+99),IF(H48>0,H48,1E+99),IF(K48>0,K48,1E+99))),F48,IF(H48=IF(COUNT(E48,H48,K48)=0,0,MIN(IF(E48>0,E48,1E+99),IF(H48>0,H48,1E+99),IF(K48>0,K48,1E+99))),I48,L48)))))),0) -> 4 | P48: =IFERROR(IF($C48<>"x",0,IF($M48=1,D48,IF($M48=2,G48,IF($M48=3,J48,IF(E48=IF(COUNT(E48,H48,K48)=0,0,MIN(IF(E48>0,E48,1E+99),IF(H48>0,H48,1E+99),IF(K48>0,K48,1E+99))),D48,IF(H48=IF(COUNT(E48,H48,K48)=0,0,MIN(IF(E48>0,E48,1E+99),IF(H48>0,H48,1E+99),IF(K48>0,K48,1E+99))),G48,J48)))))),0) -> Tile Team LLC
A49: 5 | B49: Shower & Tub Surround Tile | C49: ='Scope & Phases'!D49 -> x | E49: 2475 | F49: 4 | N49: =IFERROR(IF($C49<>"x",0,IF($M49=1,E49,IF($M49=2,H49,IF($M49=3,K49,IF(COUNT(E49,H49,K49)=0,0,MIN(IF(E49>0,E49,1E+99),IF(H49>0,H49,1E+99),IF(K49>0,K49,1E+99))))))),0) -> 2475 | O49: =IFERROR(IF($C49<>"x",0,IF($M49=1,F49,IF($M49=2,I49,IF($M49=3,L49,IF(E49=IF(COUNT(E49,H49,K49)=0,0,MIN(IF(E49>0,E49,1E+99),IF(H49>0,H49,1E+99),IF(K49>0,K49,1E+99))),F49,IF(H49=IF(COUNT(E49,H49,K49)=0,0,MIN(IF(E49>0,E49,1E+99),IF(H49>0,H49,1E+99),IF(K49>0,K49,1E+99))),I49,L49)))))),0) -> 4 | P49: =IFERROR(IF($C49<>"x",0,IF($M49=1,D49,IF($M49=2,G49,IF($M49=3,J49,IF(E49=IF(COUNT(E49,H49,K49)=0,0,MIN(IF(E49>0,E49,1E+99),IF(H49>0,H49,1E+99),IF(K49>0,K49,1E+99))),D49,IF(H49=IF(COUNT(E49,H49,K49)=0,0,MIN(IF(E49>0,E49,1E+99),IF(H49>0,H49,1E+99),IF(K49>0,K49,1E+99))),G49,J49)))))),0) -> 0
A50: 5 | B50: Backsplash Tile | C50: ='Scope & Phases'!D50 -> x | E50: 1000 | F50: 2 | N50: =IFERROR(IF($C50<>"x",0,IF($M50=1,E50,IF($M50=2,H50,IF($M50=3,K50,IF(COUNT(E50,H50,K50)=0,0,MIN(IF(E50>0,E50,1E+99),IF(H50>0,H50,1E+99),IF(K50>0,K50,1E+99))))))),0) -> 1000 | O50: =IFERROR(IF($C50<>"x",0,IF($M50=1,F50,IF($M50=2,I50,IF($M50=3,L50,IF(E50=IF(COUNT(E50,H50,K50)=0,0,MIN(IF(E50>0,E50,1E+99),IF(H50>0,H50,1E+99),IF(K50>0,K50,1E+99))),F50,IF(H50=IF(COUNT(E50,H50,K50)=0,0,MIN(IF(E50>0,E50,1E+99),IF(H50>0,H50,1E+99),IF(K50>0,K50,1E+99))),I50,L50)))))),0) -> 2 | P50: =IFERROR(IF($C50<>"x",0,IF($M50=1,D50,IF($M50=2,G50,IF($M50=3,J50,IF(E50=IF(COUNT(E50,H50,K50)=0,0,MIN(IF(E50>0,E50,1E+99),IF(H50>0,H50,1E+99),IF(K50>0,K50,1E+99))),D50,IF(H50=IF(COUNT(E50,H50,K50)=0,0,MIN(IF(E50>0,E50,1E+99),IF(H50>0,H50,1E+99),IF(K50>0,K50,1E+99))),G50,J50)))))),0) -> 0
A51: 5 | B51: LVP / Hardwood / Laminate | C51: ='Scope & Phases'!D51 -> x | D51: Desert Floors | E51: 5200 | F51: 4 | G51: Legacy Flooring | H51: 5925 | I51: 5 | J51: Saguaro Surfaces | K51: 5500 | L51: 3 | N51: =IFERROR(IF($C51<>"x",0,IF($M51=1,E51,IF($M51=2,H51,IF($M51=3,K51,IF(COUNT(E51,H51,K51)=0,0,MIN(IF(E51>0,E51,1E+99),IF(H51>0,H51,1E+99),IF(K51>0,K51,1E+99))))))),0) -> 5200 | O51: =IFERROR(IF($C51<>"x",0,IF($M51=1,F51,IF($M51=2,I51,IF($M51=3,L51,IF(E51=IF(COUNT(E51,H51,K51)=0,0,MIN(IF(E51>0,E51,1E+99),IF(H51>0,H51,1E+99),IF(K51>0,K51,1E+99))),F51,IF(H51=IF(COUNT(E51,H51,K51)=0,0,MIN(IF(E51>0,E51,1E+99),IF(H51>0,H51,1E+99),IF(K51>0,K51,1E+99))),I51,L51)))))),0) -> 4 | P51: =IFERROR(IF($C51<>"x",0,IF($M51=1,D51,IF($M51=2,G51,IF($M51=3,J51,IF(E51=IF(COUNT(E51,H51,K51)=0,0,MIN(IF(E51>0,E51,1E+99),IF(H51>0,H51,1E+99),IF(K51>0,K51,1E+99))),D51,IF(H51=IF(COUNT(E51,H51,K51)=0,0,MIN(IF(E51>0,E51,1E+99),IF(H51>0,H51,1E+99),IF(K51>0,K51,1E+99))),G51,J51)))))),0) -> Desert Floors
A52: 5 | B52: Grout, Sealer & Trim Pieces | C52: ='Scope & Phases'!D52 -> x | E52: 450 | F52: 1 | N52: =IFERROR(IF($C52<>"x",0,IF($M52=1,E52,IF($M52=2,H52,IF($M52=3,K52,IF(COUNT(E52,H52,K52)=0,0,MIN(IF(E52>0,E52,1E+99),IF(H52>0,H52,1E+99),IF(K52>0,K52,1E+99))))))),0) -> 450 | O52: =IFERROR(IF($C52<>"x",0,IF($M52=1,F52,IF($M52=2,I52,IF($M52=3,L52,IF(E52=IF(COUNT(E52,H52,K52)=0,0,MIN(IF(E52>0,E52,1E+99),IF(H52>0,H52,1E+99),IF(K52>0,K52,1E+99))),F52,IF(H52=IF(COUNT(E52,H52,K52)=0,0,MIN(IF(E52>0,E52,1E+99),IF(H52>0,H52,1E+99),IF(K52>0,K52,1E+99))),I52,L52)))))),0) -> 1 | P52: =IFERROR(IF($C52<>"x",0,IF($M52=1,D52,IF($M52=2,G52,IF($M52=3,J52,IF(E52=IF(COUNT(E52,H52,K52)=0,0,MIN(IF(E52>0,E52,1E+99),IF(H52>0,H52,1E+99),IF(K52>0,K52,1E+99))),D52,IF(H52=IF(COUNT(E52,H52,K52)=0,0,MIN(IF(E52>0,E52,1E+99),IF(H52>0,H52,1E+99),IF(K52>0,K52,1E+99))),G52,J52)))))),0) -> 0
A53: 6 | B53: Stucco / Siding | C53: ='Scope & Phases'!D53 -> x | D53: Adobe Stucco Co | E53: 2900 | F53: 5 | N53: =IFERROR(IF($C53<>"x",0,IF($M53=1,E53,IF($M53=2,H53,IF($M53=3,K53,IF(COUNT(E53,H53,K53)=0,0,MIN(IF(E53>0,E53,1E+99),IF(H53>0,H53,1E+99),IF(K53>0,K53,1E+99))))))),0) -> 2900 | O53: =IFERROR(IF($C53<>"x",0,IF($M53=1,F53,IF($M53=2,I53,IF($M53=3,L53,IF(E53=IF(COUNT(E53,H53,K53)=0,0,MIN(IF(E53>0,E53,1E+99),IF(H53>0,H53,1E+99),IF(K53>0,K53,1E+99))),F53,IF(H53=IF(COUNT(E53,H53,K53)=0,0,MIN(IF(E53>0,E53,1E+99),IF(H53>0,H53,1E+99),IF(K53>0,K53,1E+99))),I53,L53)))))),0) -> 5 | P53: =IFERROR(IF($C53<>"x",0,IF($M53=1,D53,IF($M53=2,G53,IF($M53=3,J53,IF(E53=IF(COUNT(E53,H53,K53)=0,0,MIN(IF(E53>0,E53,1E+99),IF(H53>0,H53,1E+99),IF(K53>0,K53,1E+99))),D53,IF(H53=IF(COUNT(E53,H53,K53)=0,0,MIN(IF(E53>0,E53,1E+99),IF(H53>0,H53,1E+99),IF(K53>0,K53,1E+99))),G53,J53)))))),0) -> Adobe Stucco Co
A54: 6 | B54: Fascia, Soffit & Gutters | C54: ='Scope & Phases'!D54 -> x | E54: 1400 | F54: 3 | N54: =IFERROR(IF($C54<>"x",0,IF($M54=1,E54,IF($M54=2,H54,IF($M54=3,K54,IF(COUNT(E54,H54,K54)=0,0,MIN(IF(E54>0,E54,1E+99),IF(H54>0,H54,1E+99),IF(K54>0,K54,1E+99))))))),0) -> 1400 | O54: =IFERROR(IF($C54<>"x",0,IF($M54=1,F54,IF($M54=2,I54,IF($M54=3,L54,IF(E54=IF(COUNT(E54,H54,K54)=0,0,MIN(IF(E54>0,E54,1E+99),IF(H54>0,H54,1E+99),IF(K54>0,K54,1E+99))),F54,IF(H54=IF(COUNT(E54,H54,K54)=0,0,MIN(IF(E54>0,E54,1E+99),IF(H54>0,H54,1E+99),IF(K54>0,K54,1E+99))),I54,L54)))))),0) -> 3 | P54: =IFERROR(IF($C54<>"x",0,IF($M54=1,D54,IF($M54=2,G54,IF($M54=3,J54,IF(E54=IF(COUNT(E54,H54,K54)=0,0,MIN(IF(E54>0,E54,1E+99),IF(H54>0,H54,1E+99),IF(K54>0,K54,1E+99))),D54,IF(H54=IF(COUNT(E54,H54,K54)=0,0,MIN(IF(E54>0,E54,1E+99),IF(H54>0,H54,1E+99),IF(K54>0,K54,1E+99))),G54,J54)))))),0) -> 0
A55: 6 | B55: Driveway, Walkway & Hardscape | C55: ='Scope & Phases'!D55 -> 0 | N55: =IFERROR(IF($C55<>"x",0,IF($M55=1,E55,IF($M55=2,H55,IF($M55=3,K55,IF(COUNT(E55,H55,K55)=0,0,MIN(IF(E55>0,E55,1E+99),IF(H55>0,H55,1E+99),IF(K55>0,K55,1E+99))))))),0) -> 0 | O55: =IFERROR(IF($C55<>"x",0,IF($M55=1,F55,IF($M55=2,I55,IF($M55=3,L55,IF(E55=IF(COUNT(E55,H55,K55)=0,0,MIN(IF(E55>0,E55,1E+99),IF(H55>0,H55,1E+99),IF(K55>0,K55,1E+99))),F55,IF(H55=IF(COUNT(E55,H55,K55)=0,0,MIN(IF(E55>0,E55,1E+99),IF(H55>0,H55,1E+99),IF(K55>0,K55,1E+99))),I55,L55)))))),0) -> 0 | P55: =IFERROR(IF($C55<>"x",0,IF($M55=1,D55,IF($M55=2,G55,IF($M55=3,J55,IF(E55=IF(COUNT(E55,H55,K55)=0,0,MIN(IF(E55>0,E55,1E+99),IF(H55>0,H55,1E+99),IF(K55>0,K55,1E+99))),D55,IF(H55=IF(COUNT(E55,H55,K55)=0,0,MIN(IF(E55>0,E55,1E+99),IF(H55>0,H55,1E+99),IF(K55>0,K55,1E+99))),G55,J55)))))),0) -> 0
A56: 6 | B56: Fencing & Gates | C56: ='Scope & Phases'!D56 -> x | E56: 2150 | F56: 3 | N56: =IFERROR(IF($C56<>"x",0,IF($M56=1,E56,IF($M56=2,H56,IF($M56=3,K56,IF(COUNT(E56,H56,K56)=0,0,MIN(IF(E56>0,E56,1E+99),IF(H56>0,H56,1E+99),IF(K56>0,K56,1E+99))))))),0) -> 2150 | O56: =IFERROR(IF($C56<>"x",0,IF($M56=1,F56,IF($M56=2,I56,IF($M56=3,L56,IF(E56=IF(COUNT(E56,H56,K56)=0,0,MIN(IF(E56>0,E56,1E+99),IF(H56>0,H56,1E+99),IF(K56>0,K56,1E+99))),F56,IF(H56=IF(COUNT(E56,H56,K56)=0,0,MIN(IF(E56>0,E56,1E+99),IF(H56>0,H56,1E+99),IF(K56>0,K56,1E+99))),I56,L56)))))),0) -> 3 | P56: =IFERROR(IF($C56<>"x",0,IF($M56=1,D56,IF($M56=2,G56,IF($M56=3,J56,IF(E56=IF(COUNT(E56,H56,K56)=0,0,MIN(IF(E56>0,E56,1E+99),IF(H56>0,H56,1E+99),IF(K56>0,K56,1E+99))),D56,IF(H56=IF(COUNT(E56,H56,K56)=0,0,MIN(IF(E56>0,E56,1E+99),IF(H56>0,H56,1E+99),IF(K56>0,K56,1E+99))),G56,J56)))))),0) -> 0
A57: 6 | B57: Pool Repair & Resurface | C57: ='Scope & Phases'!D57 -> 0 | N57: =IFERROR(IF($C57<>"x",0,IF($M57=1,E57,IF($M57=2,H57,IF($M57=3,K57,IF(COUNT(E57,H57,K57)=0,0,MIN(IF(E57>0,E57,1E+99),IF(H57>0,H57,1E+99),IF(K57>0,K57,1E+99))))))),0) -> 0 | O57: =IFERROR(IF($C57<>"x",0,IF($M57=1,F57,IF($M57=2,I57,IF($M57=3,L57,IF(E57=IF(COUNT(E57,H57,K57)=0,0,MIN(IF(E57>0,E57,1E+99),IF(H57>0,H57,1E+99),IF(K57>0,K57,1E+99))),F57,IF(H57=IF(COUNT(E57,H57,K57)=0,0,MIN(IF(E57>0,E57,1E+99),IF(H57>0,H57,1E+99),IF(K57>0,K57,1E+99))),I57,L57)))))),0) -> 0 | P57: =IFERROR(IF($C57<>"x",0,IF($M57=1,D57,IF($M57=2,G57,IF($M57=3,J57,IF(E57=IF(COUNT(E57,H57,K57)=0,0,MIN(IF(E57>0,E57,1E+99),IF(H57>0,H57,1E+99),IF(K57>0,K57,1E+99))),D57,IF(H57=IF(COUNT(E57,H57,K57)=0,0,MIN(IF(E57>0,E57,1E+99),IF(H57>0,H57,1E+99),IF(K57>0,K57,1E+99))),G57,J57)))))),0) -> 0
A58: 6 | B58: Exterior Paint | C58: ='Scope & Phases'!D58 -> x | D58: Brushworks AZ | E58: 3250 | F58: 4 | G58: Gilbert Painting | H58: 3700 | I58: 5 | J58: Red Rock Coatings | K58: 3450 | L58: 3 | N58: =IFERROR(IF($C58<>"x",0,IF($M58=1,E58,IF($M58=2,H58,IF($M58=3,K58,IF(COUNT(E58,H58,K58)=0,0,MIN(IF(E58>0,E58,1E+99),IF(H58>0,H58,1E+99),IF(K58>0,K58,1E+99))))))),0) -> 3250 | O58: =IFERROR(IF($C58<>"x",0,IF($M58=1,F58,IF($M58=2,I58,IF($M58=3,L58,IF(E58=IF(COUNT(E58,H58,K58)=0,0,MIN(IF(E58>0,E58,1E+99),IF(H58>0,H58,1E+99),IF(K58>0,K58,1E+99))),F58,IF(H58=IF(COUNT(E58,H58,K58)=0,0,MIN(IF(E58>0,E58,1E+99),IF(H58>0,H58,1E+99),IF(K58>0,K58,1E+99))),I58,L58)))))),0) -> 4 | P58: =IFERROR(IF($C58<>"x",0,IF($M58=1,D58,IF($M58=2,G58,IF($M58=3,J58,IF(E58=IF(COUNT(E58,H58,K58)=0,0,MIN(IF(E58>0,E58,1E+99),IF(H58>0,H58,1E+99),IF(K58>0,K58,1E+99))),D58,IF(H58=IF(COUNT(E58,H58,K58)=0,0,MIN(IF(E58>0,E58,1E+99),IF(H58>0,H58,1E+99),IF(K58>0,K58,1E+99))),G58,J58)))))),0) -> Brushworks AZ
A59: 6 | B59: Exterior Lighting | C59: ='Scope & Phases'!D59 -> x | E59: 575 | F59: 1 | N59: =IFERROR(IF($C59<>"x",0,IF($M59=1,E59,IF($M59=2,H59,IF($M59=3,K59,IF(COUNT(E59,H59,K59)=0,0,MIN(IF(E59>0,E59,1E+99),IF(H59>0,H59,1E+99),IF(K59>0,K59,1E+99))))))),0) -> 575 | O59: =IFERROR(IF($C59<>"x",0,IF($M59=1,F59,IF($M59=2,I59,IF($M59=3,L59,IF(E59=IF(COUNT(E59,H59,K59)=0,0,MIN(IF(E59>0,E59,1E+99),IF(H59>0,H59,1E+99),IF(K59>0,K59,1E+99))),F59,IF(H59=IF(COUNT(E59,H59,K59)=0,0,MIN(IF(E59>0,E59,1E+99),IF(H59>0,H59,1E+99),IF(K59>0,K59,1E+99))),I59,L59)))))),0) -> 1 | P59: =IFERROR(IF($C59<>"x",0,IF($M59=1,D59,IF($M59=2,G59,IF($M59=3,J59,IF(E59=IF(COUNT(E59,H59,K59)=0,0,MIN(IF(E59>0,E59,1E+99),IF(H59>0,H59,1E+99),IF(K59>0,K59,1E+99))),D59,IF(H59=IF(COUNT(E59,H59,K59)=0,0,MIN(IF(E59>0,E59,1E+99),IF(H59>0,H59,1E+99),IF(K59>0,K59,1E+99))),G59,J59)))))),0) -> 0
A60: 6 | B60: Landscaping | C60: ='Scope & Phases'!D60 -> x | D60: Verde Landscape | E60: 4225 | F60: 6 | G60: Cactus Creek Outdoor | H60: 4825 | I60: 7 | J60: Ironwood Grounds | K60: 4475 | L60: 5 | N60: =IFERROR(IF($C60<>"x",0,IF($M60=1,E60,IF($M60=2,H60,IF($M60=3,K60,IF(COUNT(E60,H60,K60)=0,0,MIN(IF(E60>0,E60,1E+99),IF(H60>0,H60,1E+99),IF(K60>0,K60,1E+99))))))),0) -> 4225 | O60: =IFERROR(IF($C60<>"x",0,IF($M60=1,F60,IF($M60=2,I60,IF($M60=3,L60,IF(E60=IF(COUNT(E60,H60,K60)=0,0,MIN(IF(E60>0,E60,1E+99),IF(H60>0,H60,1E+99),IF(K60>0,K60,1E+99))),F60,IF(H60=IF(COUNT(E60,H60,K60)=0,0,MIN(IF(E60>0,E60,1E+99),IF(H60>0,H60,1E+99),IF(K60>0,K60,1E+99))),I60,L60)))))),0) -> 6 | P60: =IFERROR(IF($C60<>"x",0,IF($M60=1,D60,IF($M60=2,G60,IF($M60=3,J60,IF(E60=IF(COUNT(E60,H60,K60)=0,0,MIN(IF(E60>0,E60,1E+99),IF(H60>0,H60,1E+99),IF(K60>0,K60,1E+99))),D60,IF(H60=IF(COUNT(E60,H60,K60)=0,0,MIN(IF(E60>0,E60,1E+99),IF(H60>0,H60,1E+99),IF(K60>0,K60,1E+99))),G60,J60)))))),0) -> Verde Landscape
A61: 7 | B61: Plumbing Trim | C61: ='Scope & Phases'!D61 -> x | E61: 1750 | F61: 3 | N61: =IFERROR(IF($C61<>"x",0,IF($M61=1,E61,IF($M61=2,H61,IF($M61=3,K61,IF(COUNT(E61,H61,K61)=0,0,MIN(IF(E61>0,E61,1E+99),IF(H61>0,H61,1E+99),IF(K61>0,K61,1E+99))))))),0) -> 1750 | O61: =IFERROR(IF($C61<>"x",0,IF($M61=1,F61,IF($M61=2,I61,IF($M61=3,L61,IF(E61=IF(COUNT(E61,H61,K61)=0,0,MIN(IF(E61>0,E61,1E+99),IF(H61>0,H61,1E+99),IF(K61>0,K61,1E+99))),F61,IF(H61=IF(COUNT(E61,H61,K61)=0,0,MIN(IF(E61>0,E61,1E+99),IF(H61>0,H61,1E+99),IF(K61>0,K61,1E+99))),I61,L61)))))),0) -> 3 | P61: =IFERROR(IF($C61<>"x",0,IF($M61=1,D61,IF($M61=2,G61,IF($M61=3,J61,IF(E61=IF(COUNT(E61,H61,K61)=0,0,MIN(IF(E61>0,E61,1E+99),IF(H61>0,H61,1E+99),IF(K61>0,K61,1E+99))),D61,IF(H61=IF(COUNT(E61,H61,K61)=0,0,MIN(IF(E61>0,E61,1E+99),IF(H61>0,H61,1E+99),IF(K61>0,K61,1E+99))),G61,J61)))))),0) -> 0
A62: 7 | B62: Electrical Trim | C62: ='Scope & Phases'!D62 -> x | E62: 1550 | F62: 3 | N62: =IFERROR(IF($C62<>"x",0,IF($M62=1,E62,IF($M62=2,H62,IF($M62=3,K62,IF(COUNT(E62,H62,K62)=0,0,MIN(IF(E62>0,E62,1E+99),IF(H62>0,H62,1E+99),IF(K62>0,K62,1E+99))))))),0) -> 1550 | O62: =IFERROR(IF($C62<>"x",0,IF($M62=1,F62,IF($M62=2,I62,IF($M62=3,L62,IF(E62=IF(COUNT(E62,H62,K62)=0,0,MIN(IF(E62>0,E62,1E+99),IF(H62>0,H62,1E+99),IF(K62>0,K62,1E+99))),F62,IF(H62=IF(COUNT(E62,H62,K62)=0,0,MIN(IF(E62>0,E62,1E+99),IF(H62>0,H62,1E+99),IF(K62>0,K62,1E+99))),I62,L62)))))),0) -> 3 | P62: =IFERROR(IF($C62<>"x",0,IF($M62=1,D62,IF($M62=2,G62,IF($M62=3,J62,IF(E62=IF(COUNT(E62,H62,K62)=0,0,MIN(IF(E62>0,E62,1E+99),IF(H62>0,H62,1E+99),IF(K62>0,K62,1E+99))),D62,IF(H62=IF(COUNT(E62,H62,K62)=0,0,MIN(IF(E62>0,E62,1E+99),IF(H62>0,H62,1E+99),IF(K62>0,K62,1E+99))),G62,J62)))))),0) -> 0
A63: 7 | B63: HVAC Start-up & Registers | C63: ='Scope & Phases'!D63 -> x | E63: 700 | F63: 2 | N63: =IFERROR(IF($C63<>"x",0,IF($M63=1,E63,IF($M63=2,H63,IF($M63=3,K63,IF(COUNT(E63,H63,K63)=0,0,MIN(IF(E63>0,E63,1E+99),IF(H63>0,H63,1E+99),IF(K63>0,K63,1E+99))))))),0) -> 700 | O63: =IFERROR(IF($C63<>"x",0,IF($M63=1,F63,IF($M63=2,I63,IF($M63=3,L63,IF(E63=IF(COUNT(E63,H63,K63)=0,0,MIN(IF(E63>0,E63,1E+99),IF(H63>0,H63,1E+99),IF(K63>0,K63,1E+99))),F63,IF(H63=IF(COUNT(E63,H63,K63)=0,0,MIN(IF(E63>0,E63,1E+99),IF(H63>0,H63,1E+99),IF(K63>0,K63,1E+99))),I63,L63)))))),0) -> 2 | P63: =IFERROR(IF($C63<>"x",0,IF($M63=1,D63,IF($M63=2,G63,IF($M63=3,J63,IF(E63=IF(COUNT(E63,H63,K63)=0,0,MIN(IF(E63>0,E63,1E+99),IF(H63>0,H63,1E+99),IF(K63>0,K63,1E+99))),D63,IF(H63=IF(COUNT(E63,H63,K63)=0,0,MIN(IF(E63>0,E63,1E+99),IF(H63>0,H63,1E+99),IF(K63>0,K63,1E+99))),G63,J63)))))),0) -> 0
A64: 7 | B64: Shower Glass & Mirrors | C64: ='Scope & Phases'!D64 -> x | E64: 1850 | F64: 2 | N64: =IFERROR(IF($C64<>"x",0,IF($M64=1,E64,IF($M64=2,H64,IF($M64=3,K64,IF(COUNT(E64,H64,K64)=0,0,MIN(IF(E64>0,E64,1E+99),IF(H64>0,H64,1E+99),IF(K64>0,K64,1E+99))))))),0) -> 1850 | O64: =IFERROR(IF($C64<>"x",0,IF($M64=1,F64,IF($M64=2,I64,IF($M64=3,L64,IF(E64=IF(COUNT(E64,H64,K64)=0,0,MIN(IF(E64>0,E64,1E+99),IF(H64>0,H64,1E+99),IF(K64>0,K64,1E+99))),F64,IF(H64=IF(COUNT(E64,H64,K64)=0,0,MIN(IF(E64>0,E64,1E+99),IF(H64>0,H64,1E+99),IF(K64>0,K64,1E+99))),I64,L64)))))),0) -> 2 | P64: =IFERROR(IF($C64<>"x",0,IF($M64=1,D64,IF($M64=2,G64,IF($M64=3,J64,IF(E64=IF(COUNT(E64,H64,K64)=0,0,MIN(IF(E64>0,E64,1E+99),IF(H64>0,H64,1E+99),IF(K64>0,K64,1E+99))),D64,IF(H64=IF(COUNT(E64,H64,K64)=0,0,MIN(IF(E64>0,E64,1E+99),IF(H64>0,H64,1E+99),IF(K64>0,K64,1E+99))),G64,J64)))))),0) -> 0
A65: 7 | B65: Bath Accessories | C65: ='Scope & Phases'!D65 -> x | E65: 450 | F65: 1 | N65: =IFERROR(IF($C65<>"x",0,IF($M65=1,E65,IF($M65=2,H65,IF($M65=3,K65,IF(COUNT(E65,H65,K65)=0,0,MIN(IF(E65>0,E65,1E+99),IF(H65>0,H65,1E+99),IF(K65>0,K65,1E+99))))))),0) -> 450 | O65: =IFERROR(IF($C65<>"x",0,IF($M65=1,F65,IF($M65=2,I65,IF($M65=3,L65,IF(E65=IF(COUNT(E65,H65,K65)=0,0,MIN(IF(E65>0,E65,1E+99),IF(H65>0,H65,1E+99),IF(K65>0,K65,1E+99))),F65,IF(H65=IF(COUNT(E65,H65,K65)=0,0,MIN(IF(E65>0,E65,1E+99),IF(H65>0,H65,1E+99),IF(K65>0,K65,1E+99))),I65,L65)))))),0) -> 1 | P65: =IFERROR(IF($C65<>"x",0,IF($M65=1,D65,IF($M65=2,G65,IF($M65=3,J65,IF(E65=IF(COUNT(E65,H65,K65)=0,0,MIN(IF(E65>0,E65,1E+99),IF(H65>0,H65,1E+99),IF(K65>0,K65,1E+99))),D65,IF(H65=IF(COUNT(E65,H65,K65)=0,0,MIN(IF(E65>0,E65,1E+99),IF(H65>0,H65,1E+99),IF(K65>0,K65,1E+99))),G65,J65)))))),0) -> 0
A66: 7 | B66: Appliances | C66: ='Scope & Phases'!D66 -> x | D66: Spencer's TV & Appliance | E66: 4050 | F66: 1 | G66: Best Buy | H66: 4625 | I66: 2 | J66: Ferguson | K66: 4300 | L66: 1 | N66: =IFERROR(IF($C66<>"x",0,IF($M66=1,E66,IF($M66=2,H66,IF($M66=3,K66,IF(COUNT(E66,H66,K66)=0,0,MIN(IF(E66>0,E66,1E+99),IF(H66>0,H66,1E+99),IF(K66>0,K66,1E+99))))))),0) -> 4050 | O66: =IFERROR(IF($C66<>"x",0,IF($M66=1,F66,IF($M66=2,I66,IF($M66=3,L66,IF(E66=IF(COUNT(E66,H66,K66)=0,0,MIN(IF(E66>0,E66,1E+99),IF(H66>0,H66,1E+99),IF(K66>0,K66,1E+99))),F66,IF(H66=IF(COUNT(E66,H66,K66)=0,0,MIN(IF(E66>0,E66,1E+99),IF(H66>0,H66,1E+99),IF(K66>0,K66,1E+99))),I66,L66)))))),0) -> 1 | P66: =IFERROR(IF($C66<>"x",0,IF($M66=1,D66,IF($M66=2,G66,IF($M66=3,J66,IF(E66=IF(COUNT(E66,H66,K66)=0,0,MIN(IF(E66>0,E66,1E+99),IF(H66>0,H66,1E+99),IF(K66>0,K66,1E+99))),D66,IF(H66=IF(COUNT(E66,H66,K66)=0,0,MIN(IF(E66>0,E66,1E+99),IF(H66>0,H66,1E+99),IF(K66>0,K66,1E+99))),G66,J66)))))),0) -> Spencer's TV & Appliance
A67: 7 | B67: Garage Door & Opener | C67: ='Scope & Phases'!D67 -> x | E67: 1325 | F67: 1 | N67: =IFERROR(IF($C67<>"x",0,IF($M67=1,E67,IF($M67=2,H67,IF($M67=3,K67,IF(COUNT(E67,H67,K67)=0,0,MIN(IF(E67>0,E67,1E+99),IF(H67>0,H67,1E+99),IF(K67>0,K67,1E+99))))))),0) -> 1325 | O67: =IFERROR(IF($C67<>"x",0,IF($M67=1,F67,IF($M67=2,I67,IF($M67=3,L67,IF(E67=IF(COUNT(E67,H67,K67)=0,0,MIN(IF(E67>0,E67,1E+99),IF(H67>0,H67,1E+99),IF(K67>0,K67,1E+99))),F67,IF(H67=IF(COUNT(E67,H67,K67)=0,0,MIN(IF(E67>0,E67,1E+99),IF(H67>0,H67,1E+99),IF(K67>0,K67,1E+99))),I67,L67)))))),0) -> 1 | P67: =IFERROR(IF($C67<>"x",0,IF($M67=1,D67,IF($M67=2,G67,IF($M67=3,J67,IF(E67=IF(COUNT(E67,H67,K67)=0,0,MIN(IF(E67>0,E67,1E+99),IF(H67>0,H67,1E+99),IF(K67>0,K67,1E+99))),D67,IF(H67=IF(COUNT(E67,H67,K67)=0,0,MIN(IF(E67>0,E67,1E+99),IF(H67>0,H67,1E+99),IF(K67>0,K67,1E+99))),G67,J67)))))),0) -> 0
A68: 7 | B68: Life Safety & Final Inspections | C68: ='Scope & Phases'!D68 -> x | E68: 400 | F68: 2 | N68: =IFERROR(IF($C68<>"x",0,IF($M68=1,E68,IF($M68=2,H68,IF($M68=3,K68,IF(COUNT(E68,H68,K68)=0,0,MIN(IF(E68>0,E68,1E+99),IF(H68>0,H68,1E+99),IF(K68>0,K68,1E+99))))))),0) -> 400 | O68: =IFERROR(IF($C68<>"x",0,IF($M68=1,F68,IF($M68=2,I68,IF($M68=3,L68,IF(E68=IF(COUNT(E68,H68,K68)=0,0,MIN(IF(E68>0,E68,1E+99),IF(H68>0,H68,1E+99),IF(K68>0,K68,1E+99))),F68,IF(H68=IF(COUNT(E68,H68,K68)=0,0,MIN(IF(E68>0,E68,1E+99),IF(H68>0,H68,1E+99),IF(K68>0,K68,1E+99))),I68,L68)))))),0) -> 2 | P68: =IFERROR(IF($C68<>"x",0,IF($M68=1,D68,IF($M68=2,G68,IF($M68=3,J68,IF(E68=IF(COUNT(E68,H68,K68)=0,0,MIN(IF(E68>0,E68,1E+99),IF(H68>0,H68,1E+99),IF(K68>0,K68,1E+99))),D68,IF(H68=IF(COUNT(E68,H68,K68)=0,0,MIN(IF(E68>0,E68,1E+99),IF(H68>0,H68,1E+99),IF(K68>0,K68,1E+99))),G68,J68)))))),0) -> 0
A69: 8 | B69: Punch List & Touch-up | C69: ='Scope & Phases'!D69 -> x | E69: 1400 | F69: 4 | N69: =IFERROR(IF($C69<>"x",0,IF($M69=1,E69,IF($M69=2,H69,IF($M69=3,K69,IF(COUNT(E69,H69,K69)=0,0,MIN(IF(E69>0,E69,1E+99),IF(H69>0,H69,1E+99),IF(K69>0,K69,1E+99))))))),0) -> 1400 | O69: =IFERROR(IF($C69<>"x",0,IF($M69=1,F69,IF($M69=2,I69,IF($M69=3,L69,IF(E69=IF(COUNT(E69,H69,K69)=0,0,MIN(IF(E69>0,E69,1E+99),IF(H69>0,H69,1E+99),IF(K69>0,K69,1E+99))),F69,IF(H69=IF(COUNT(E69,H69,K69)=0,0,MIN(IF(E69>0,E69,1E+99),IF(H69>0,H69,1E+99),IF(K69>0,K69,1E+99))),I69,L69)))))),0) -> 4 | P69: =IFERROR(IF($C69<>"x",0,IF($M69=1,D69,IF($M69=2,G69,IF($M69=3,J69,IF(E69=IF(COUNT(E69,H69,K69)=0,0,MIN(IF(E69>0,E69,1E+99),IF(H69>0,H69,1E+99),IF(K69>0,K69,1E+99))),D69,IF(H69=IF(COUNT(E69,H69,K69)=0,0,MIN(IF(E69>0,E69,1E+99),IF(H69>0,H69,1E+99),IF(K69>0,K69,1E+99))),G69,J69)))))),0) -> 0
A70: 8 | B70: Carpet | C70: ='Scope & Phases'!D70 -> x | D70: Desert Floors | E70: 1925 | F70: 2 | N70: =IFERROR(IF($C70<>"x",0,IF($M70=1,E70,IF($M70=2,H70,IF($M70=3,K70,IF(COUNT(E70,H70,K70)=0,0,MIN(IF(E70>0,E70,1E+99),IF(H70>0,H70,1E+99),IF(K70>0,K70,1E+99))))))),0) -> 1925 | O70: =IFERROR(IF($C70<>"x",0,IF($M70=1,F70,IF($M70=2,I70,IF($M70=3,L70,IF(E70=IF(COUNT(E70,H70,K70)=0,0,MIN(IF(E70>0,E70,1E+99),IF(H70>0,H70,1E+99),IF(K70>0,K70,1E+99))),F70,IF(H70=IF(COUNT(E70,H70,K70)=0,0,MIN(IF(E70>0,E70,1E+99),IF(H70>0,H70,1E+99),IF(K70>0,K70,1E+99))),I70,L70)))))),0) -> 2 | P70: =IFERROR(IF($C70<>"x",0,IF($M70=1,D70,IF($M70=2,G70,IF($M70=3,J70,IF(E70=IF(COUNT(E70,H70,K70)=0,0,MIN(IF(E70>0,E70,1E+99),IF(H70>0,H70,1E+99),IF(K70>0,K70,1E+99))),D70,IF(H70=IF(COUNT(E70,H70,K70)=0,0,MIN(IF(E70>0,E70,1E+99),IF(H70>0,H70,1E+99),IF(K70>0,K70,1E+99))),G70,J70)))))),0) -> Desert Floors
A71: 8 | B71: Final Clean | C71: ='Scope & Phases'!D71 -> x | D71: Sparkle Crew | E71: 625 | F71: 2 | N71: =IFERROR(IF($C71<>"x",0,IF($M71=1,E71,IF($M71=2,H71,IF($M71=3,K71,IF(COUNT(E71,H71,K71)=0,0,MIN(IF(E71>0,E71,1E+99),IF(H71>0,H71,1E+99),IF(K71>0,K71,1E+99))))))),0) -> 625 | O71: =IFERROR(IF($C71<>"x",0,IF($M71=1,F71,IF($M71=2,I71,IF($M71=3,L71,IF(E71=IF(COUNT(E71,H71,K71)=0,0,MIN(IF(E71>0,E71,1E+99),IF(H71>0,H71,1E+99),IF(K71>0,K71,1E+99))),F71,IF(H71=IF(COUNT(E71,H71,K71)=0,0,MIN(IF(E71>0,E71,1E+99),IF(H71>0,H71,1E+99),IF(K71>0,K71,1E+99))),I71,L71)))))),0) -> 2 | P71: =IFERROR(IF($C71<>"x",0,IF($M71=1,D71,IF($M71=2,G71,IF($M71=3,J71,IF(E71=IF(COUNT(E71,H71,K71)=0,0,MIN(IF(E71>0,E71,1E+99),IF(H71>0,H71,1E+99),IF(K71>0,K71,1E+99))),D71,IF(H71=IF(COUNT(E71,H71,K71)=0,0,MIN(IF(E71>0,E71,1E+99),IF(H71>0,H71,1E+99),IF(K71>0,K71,1E+99))),G71,J71)))))),0) -> Sparkle Crew
A72: 8 | B72: Staging | C72: ='Scope & Phases'!D72 -> x | D72: Staged AZ | E72: 2200 | F72: 2 | N72: =IFERROR(IF($C72<>"x",0,IF($M72=1,E72,IF($M72=2,H72,IF($M72=3,K72,IF(COUNT(E72,H72,K72)=0,0,MIN(IF(E72>0,E72,1E+99),IF(H72>0,H72,1E+99),IF(K72>0,K72,1E+99))))))),0) -> 2200 | O72: =IFERROR(IF($C72<>"x",0,IF($M72=1,F72,IF($M72=2,I72,IF($M72=3,L72,IF(E72=IF(COUNT(E72,H72,K72)=0,0,MIN(IF(E72>0,E72,1E+99),IF(H72>0,H72,1E+99),IF(K72>0,K72,1E+99))),F72,IF(H72=IF(COUNT(E72,H72,K72)=0,0,MIN(IF(E72>0,E72,1E+99),IF(H72>0,H72,1E+99),IF(K72>0,K72,1E+99))),I72,L72)))))),0) -> 2 | P72: =IFERROR(IF($C72<>"x",0,IF($M72=1,D72,IF($M72=2,G72,IF($M72=3,J72,IF(E72=IF(COUNT(E72,H72,K72)=0,0,MIN(IF(E72>0,E72,1E+99),IF(H72>0,H72,1E+99),IF(K72>0,K72,1E+99))),D72,IF(H72=IF(COUNT(E72,H72,K72)=0,0,MIN(IF(E72>0,E72,1E+99),IF(H72>0,H72,1E+99),IF(K72>0,K72,1E+99))),G72,J72)))))),0) -> Staged AZ
A73: 8 | B73: Warranty & Callback Reserve | C73: ='Scope & Phases'!D73 -> x | E73: 975 | F73: 0 | N73: =IFERROR(IF($C73<>"x",0,IF($M73=1,E73,IF($M73=2,H73,IF($M73=3,K73,IF(COUNT(E73,H73,K73)=0,0,MIN(IF(E73>0,E73,1E+99),IF(H73>0,H73,1E+99),IF(K73>0,K73,1E+99))))))),0) -> 975 | O73: =IFERROR(IF($C73<>"x",0,IF($M73=1,F73,IF($M73=2,I73,IF($M73=3,L73,IF(E73=IF(COUNT(E73,H73,K73)=0,0,MIN(IF(E73>0,E73,1E+99),IF(H73>0,H73,1E+99),IF(K73>0,K73,1E+99))),F73,IF(H73=IF(COUNT(E73,H73,K73)=0,0,MIN(IF(E73>0,E73,1E+99),IF(H73>0,H73,1E+99),IF(K73>0,K73,1E+99))),I73,L73)))))),0) -> 0 | P73: =IFERROR(IF($C73<>"x",0,IF($M73=1,D73,IF($M73=2,G73,IF($M73=3,J73,IF(E73=IF(COUNT(E73,H73,K73)=0,0,MIN(IF(E73>0,E73,1E+99),IF(H73>0,H73,1E+99),IF(K73>0,K73,1E+99))),D73,IF(H73=IF(COUNT(E73,H73,K73)=0,0,MIN(IF(E73>0,E73,1E+99),IF(H73>0,H73,1E+99),IF(K73>0,K73,1E+99))),G73,J73)))))),0) -> 0

Sheet Budget & Schedule
A1: Budget & Schedule
A2: Your bids, rolled up. Phases run one after another; jobs inside a phase run together.
A5: Total rehab budget | D5: =SUMIF('Scope & Phases'!$D$8:$D$73,"x",'Scope & Phases'!$E$8:$E$73) -> 129325
A6: Cost per square foot | D6: =IFERROR('Budget & Schedule'!$D$5/'Your Deal'!$D$9,0) -> 69.52957
A7: Calendar days on site | D7: =IFERROR(MAX(G12:G25)-'Your Deal'!$D$31+1,0) -> 155
A8: Months of carry | D8: =IFERROR('Budget & Schedule'!$D$7/30.44,0) -> 5.0919842
A11: Ph | B11: Phase | C11: Jobs | D11: Budget | E11: Days | F11: Starts | G11: Finishes
A12: A | B12: Pre-Construction & General Conditions | C12: =COUNTIFS('Scope & Phases'!$A$8:$A$73,"A",'Scope & Phases'!$D$8:$D$73,"x") -> 6 | D12: =SUMIFS('Scope & Phases'!$E$8:$E$73,'Scope & Phases'!$A$8:$A$73,"A",'Scope & Phases'!$D$8:$D$73,"x") -> 14925 | E12: =IFERROR(SUMIFS('Scope & Phases'!$F$8:$F$73,'Scope & Phases'!$A$8:$A$73,"A",'Scope & Phases'!$D$8:$D$73,"x"),0) -> 16 | F12: ='Your Deal'!$D$31 -> 46314 | G12: =IF(E12=0,F12-1,F12+E12-1) -> 46329
A13: 1 | B13: Demolition, Foundation & Underground | C13: =COUNTIFS('Scope & Phases'!$A$8:$A$73,"1",'Scope & Phases'!$D$8:$D$73,"x") -> 3 | D13: =SUMIFS('Scope & Phases'!$E$8:$E$73,'Scope & Phases'!$A$8:$A$73,"1",'Scope & Phases'!$D$8:$D$73,"x") -> 6000 | E13: =IFERROR(SUMIFS('Scope & Phases'!$F$8:$F$73,'Scope & Phases'!$A$8:$A$73,"1",'Scope & Phases'!$D$8:$D$73,"x"),0) -> 9 | F13: =G12+1 -> 46330 | G13: =IF(E13=0,F13-1,F13+E13-1) -> 46338
A14: 2 | B14: Framing, Roofing & Rough MEP | C14: =COUNTIFS('Scope & Phases'!$A$8:$A$73,"2",'Scope & Phases'!$D$8:$D$73,"x") -> 8 | D14: =SUMIFS('Scope & Phases'!$E$8:$E$73,'Scope & Phases'!$A$8:$A$73,"2",'Scope & Phases'!$D$8:$D$73,"x") -> 32925 | E14: =IFERROR(SUMIFS('Scope & Phases'!$F$8:$F$73,'Scope & Phases'!$A$8:$A$73,"2",'Scope & Phases'!$D$8:$D$73,"x"),0) -> 33 | F14: =G13+1 -> 46339 | G14: =IF(E14=0,F14-1,F14+E14-1) -> 46371
A15: 3 | B15: Insulation, Drywall, Doors, Trim & Paint | C15: =COUNTIFS('Scope & Phases'!$A$8:$A$73,"3",'Scope & Phases'!$D$8:$D$73,"x") -> 5 | D15: =SUMIFS('Scope & Phases'!$E$8:$E$73,'Scope & Phases'!$A$8:$A$73,"3",'Scope & Phases'!$D$8:$D$73,"x") -> 16100 | E15: =IFERROR(SUMIFS('Scope & Phases'!$F$8:$F$73,'Scope & Phases'!$A$8:$A$73,"3",'Scope & Phases'!$D$8:$D$73,"x"),0) -> 22 | F15: =G14+1 -> 46372 | G15: =IF(E15=0,F15-1,F15+E15-1) -> 46393
A16: 4 | B16: Cabinets & Countertops | C16: =COUNTIFS('Scope & Phases'!$A$8:$A$73,"4",'Scope & Phases'!$D$8:$D$73,"x") -> 5 | D16: =SUMIFS('Scope & Phases'!$E$8:$E$73,'Scope & Phases'!$A$8:$A$73,"4",'Scope & Phases'!$D$8:$D$73,"x") -> 12625 | E16: =IFERROR(SUMIFS('Scope & Phases'!$F$8:$F$73,'Scope & Phases'!$A$8:$A$73,"4",'Scope & Phases'!$D$8:$D$73,"x"),0) -> 11 | F16: =G15+1 -> 46394 | G16: =IF(E16=0,F16-1,F16+E16-1) -> 46404
A17: 5 | B17: Tile & Flooring | C17: =COUNTIFS('Scope & Phases'!$A$8:$A$73,"5",'Scope & Phases'!$D$8:$D$73,"x") -> 6 | D17: =SUMIFS('Scope & Phases'!$E$8:$E$73,'Scope & Phases'!$A$8:$A$73,"5",'Scope & Phases'!$D$8:$D$73,"x") -> 13050 | E17: =IFERROR(SUMIFS('Scope & Phases'!$F$8:$F$73,'Scope & Phases'!$A$8:$A$73,"5",'Scope & Phases'!$D$8:$D$73,"x"),0) -> 17 | F17: =G16+1 -> 46405 | G17: =IF(E17=0,F17-1,F17+E17-1) -> 46421
A18: 6 | B18: Exterior & Landscaping | C18: =COUNTIFS('Scope & Phases'!$A$8:$A$73,"6",'Scope & Phases'!$D$8:$D$73,"x") -> 6 | D18: =SUMIFS('Scope & Phases'!$E$8:$E$73,'Scope & Phases'!$A$8:$A$73,"6",'Scope & Phases'!$D$8:$D$73,"x") -> 14500 | E18: =IFERROR(SUMIFS('Scope & Phases'!$F$8:$F$73,'Scope & Phases'!$A$8:$A$73,"6",'Scope & Phases'!$D$8:$D$73,"x"),0) -> 22 | F18: =G17+1 -> 46422 | G18: =IF(E18=0,F18-1,F18+E18-1) -> 46443
A19: 7 | B19: MEP Finishes, Glass & Appliances | C19: =COUNTIFS('Scope & Phases'!$A$8:$A$73,"7",'Scope & Phases'!$D$8:$D$73,"x") -> 8 | D19: =SUMIFS('Scope & Phases'!$E$8:$E$73,'Scope & Phases'!$A$8:$A$73,"7",'Scope & Phases'!$D$8:$D$73,"x") -> 12075 | E19: =IFERROR(SUMIFS('Scope & Phases'!$F$8:$F$73,'Scope & Phases'!$A$8:$A$73,"7",'Scope & Phases'!$D$8:$D$73,"x"),0) -> 15 | F19: =G18+1 -> 46444 | G19: =IF(E19=0,F19-1,F19+E19-1) -> 46458
A20: 8 | B20: Punch, Carpet & Final Clean | C20: =COUNTIFS('Scope & Phases'!$A$8:$A$73,"8",'Scope & Phases'!$D$8:$D$73,"x") -> 5 | D20: =SUMIFS('Scope & Phases'!$E$8:$E$73,'Scope & Phases'!$A$8:$A$73,"8",'Scope & Phases'!$D$8:$D$73,"x") -> 7125 | E20: =IFERROR(SUMIFS('Scope & Phases'!$F$8:$F$73,'Scope & Phases'!$A$8:$A$73,"8",'Scope & Phases'!$D$8:$D$73,"x"),0) -> 10 | F20: =G19+1 -> 46459 | G20: =IF(E20=0,F20-1,F20+E20-1) -> 46468
B21: TOTAL | C21: =COUNTIF('Scope & Phases'!$D$8:$D$73,"x") -> 52 | D21: =SUM(D12:D20) -> 129325 | G21: =MAX(G12:G20) -> 46468
A23: A phase takes as long as its jobs added together. On a house this size one trade works at a time.
A24: Days come from what each sub quoted on the Bid Comparison sheet — they are calendar days, not working days.

Sheet Draw Schedule
A1: Draw Schedule
A2: One draw per phase. Request when the phase finishes; the money lands later.
A6: The gap between 'Request on' and 'Funded on' is the number of days you told us your lender takes.
A8: Draw | B8: Phase | C8: Phase budget | D8: Holdback | E8: You receive | F8: Request on | G8: Funded on
A9: 1 | B9: ='Budget & Schedule'!B12 -> Pre-Construction & General Conditions | C9: ='Budget & Schedule'!D12 -> 14925 | D9: =-C9*'Your Deal'!$D$35 -> -1492.5 | E9: =C9+D9 -> 13432.5 | F9: ='Budget & Schedule'!G12 -> 46329 | G9: =IF(C9=0,"",F9+'Your Deal'!$D$24) -> 46339
A10: 2 | B10: ='Budget & Schedule'!B13 -> Demolition, Foundation & Underground | C10: ='Budget & Schedule'!D13 -> 6000 | D10: =-C10*'Your Deal'!$D$35 -> -600 | E10: =C10+D10 -> 5400 | F10: ='Budget & Schedule'!G13 -> 46338 | G10: =IF(C10=0,"",F10+'Your Deal'!$D$24) -> 46348
A11: 3 | B11: ='Budget & Schedule'!B14 -> Framing, Roofing & Rough MEP | C11: ='Budget & Schedule'!D14 -> 32925 | D11: =-C11*'Your Deal'!$D$35 -> -3292.5 | E11: =C11+D11 -> 29632.5 | F11: ='Budget & Schedule'!G14 -> 46371 | G11: =IF(C11=0,"",F11+'Your Deal'!$D$24) -> 46381
A12: 4 | B12: ='Budget & Schedule'!B15 -> Insulation, Drywall, Doors, Trim & Paint | C12: ='Budget & Schedule'!D15 -> 16100 | D12: =-C12*'Your Deal'!$D$35 -> -1610 | E12: =C12+D12 -> 14490 | F12: ='Budget & Schedule'!G15 -> 46393 | G12: =IF(C12=0,"",F12+'Your Deal'!$D$24) -> 46403
A13: 5 | B13: ='Budget & Schedule'!B16 -> Cabinets & Countertops | C13: ='Budget & Schedule'!D16 -> 12625 | D13: =-C13*'Your Deal'!$D$35 -> -1262.5 | E13: =C13+D13 -> 11362.5 | F13: ='Budget & Schedule'!G16 -> 46404 | G13: =IF(C13=0,"",F13+'Your Deal'!$D$24) -> 46414
A14: 6 | B14: ='Budget & Schedule'!B17 -> Tile & Flooring | C14: ='Budget & Schedule'!D17 -> 13050 | D14: =-C14*'Your Deal'!$D$35 -> -1305 | E14: =C14+D14 -> 11745 | F14: ='Budget & Schedule'!G17 -> 46421 | G14: =IF(C14=0,"",F14+'Your Deal'!$D$24) -> 46431
A15: 7 | B15: ='Budget & Schedule'!B18 -> Exterior & Landscaping | C15: ='Budget & Schedule'!D18 -> 14500 | D15: =-C15*'Your Deal'!$D$35 -> -1450 | E15: =C15+D15 -> 13050 | F15: ='Budget & Schedule'!G18 -> 46443 | G15: =IF(C15=0,"",F15+'Your Deal'!$D$24) -> 46453
A16: 8 | B16: ='Budget & Schedule'!B19 -> MEP Finishes, Glass & Appliances | C16: ='Budget & Schedule'!D19 -> 12075 | D16: =-C16*'Your Deal'!$D$35 -> -1207.5 | E16: =C16+D16 -> 10867.5 | F16: ='Budget & Schedule'!G19 -> 46458 | G16: =IF(C16=0,"",F16+'Your Deal'!$D$24) -> 46468
A17: 9 | B17: ='Budget & Schedule'!B20 -> Punch, Carpet & Final Clean | C17: ='Budget & Schedule'!D20 -> 7125 | D17: =-C17*'Your Deal'!$D$35 -> -712.5 | E17: =C17+D17 -> 6412.5 | F17: ='Budget & Schedule'!G20 -> 46468 | G17: =IF(C17=0,"",F17+'Your Deal'!$D$24) -> 46478
B18: TOTAL | C18: =SUM(C9:C17) -> 129325 | D18: =SUM(D9:D17) -> -12932.5 | E18: =SUM(E9:E17) -> 116392.5
A20: Holdback is released at completion. Until then it is money you have spent and not been paid for.

Sheet Cash & Float
A1: Cash & Float
A2: What this job costs you to carry between paying subs and getting funded.
A6: You pay a deposit when a phase starts and the balance when it finishes. The draw arrives days after that.
A9: Ph | B9: Phase | C9: Deposit out | D9: Balance out | E9: Draw in | F9: On this date | G9: Cash position
A10: A | B10: ='Budget & Schedule'!B12 -> Pre-Construction & General Conditions | C10: =-'Budget & Schedule'!D12*'Your Deal'!$D$33 -> -7462.5 | D10: =-'Budget & Schedule'!D12*(1-'Your Deal'!$D$33) -> -7462.5 | E10: ='Draw Schedule'!E9 -> 13432.5 | F10: ='Budget & Schedule'!G12 -> 46329 | G10: ='Your Deal'!$D$26+SUMIF($F$10:$F$18,"<="&$F10,$C$10:$C$18)+SUMIF($F$10:$F$18,"<="&$F10,$D$10:$D$18)+SUMIF('Draw Schedule'!$G$9:$G$17,"<="&$F10,'Draw Schedule'!$E$9:$E$17) -> 45075
A11: 1 | B11: ='Budget & Schedule'!B13 -> Demolition, Foundation & Underground | C11: =-'Budget & Schedule'!D13*'Your Deal'!$D$33 -> -3000 | D11: =-'Budget & Schedule'!D13*(1-'Your Deal'!$D$33) -> -3000 | E11: ='Draw Schedule'!E10 -> 5400 | F11: ='Budget & Schedule'!G13 -> 46338 | G11: ='Your Deal'!$D$26+SUMIF($F$10:$F$18,"<="&$F11,$C$10:$C$18)+SUMIF($F$10:$F$18,"<="&$F11,$D$10:$D$18)+SUMIF('Draw Schedule'!$G$9:$G$17,"<="&$F11,'Draw Schedule'!$E$9:$E$17) -> 39075
A12: 2 | B12: ='Budget & Schedule'!B14 -> Framing, Roofing & Rough MEP | C12: =-'Budget & Schedule'!D14*'Your Deal'!$D$33 -> -16462.5 | D12: =-'Budget & Schedule'!D14*(1-'Your Deal'!$D$33) -> -16462.5 | E12: ='Draw Schedule'!E11 -> 29632.5 | F12: ='Budget & Schedule'!G14 -> 46371 | G12: ='Your Deal'!$D$26+SUMIF($F$10:$F$18,"<="&$F12,$C$10:$C$18)+SUMIF($F$10:$F$18,"<="&$F12,$D$10:$D$18)+SUMIF('Draw Schedule'!$G$9:$G$17,"<="&$F12,'Draw Schedule'!$E$9:$E$17) -> 24982.5
A13: 3 | B13: ='Budget & Schedule'!B15 -> Insulation, Drywall, Doors, Trim & Paint | C13: =-'Budget & Schedule'!D15*'Your Deal'!$D$33 -> -8050 | D13: =-'Budget & Schedule'!D15*(1-'Your Deal'!$D$33) -> -8050 | E13: ='Draw Schedule'!E12 -> 14490 | F13: ='Budget & Schedule'!G15 -> 46393 | G13: ='Your Deal'!$D$26+SUMIF($F$10:$F$18,"<="&$F13,$C$10:$C$18)+SUMIF($F$10:$F$18,"<="&$F13,$D$10:$D$18)+SUMIF('Draw Schedule'!$G$9:$G$17,"<="&$F13,'Draw Schedule'!$E$9:$E$17) -> 38515
A14: 4 | B14: ='Budget & Schedule'!B16 -> Cabinets & Countertops | C14: =-'Budget & Schedule'!D16*'Your Deal'!$D$33 -> -6312.5 | D14: =-'Budget & Schedule'!D16*(1-'Your Deal'!$D$33) -> -6312.5 | E14: ='Draw Schedule'!E13 -> 11362.5 | F14: ='Budget & Schedule'!G16 -> 46404 | G14: ='Your Deal'!$D$26+SUMIF($F$10:$F$18,"<="&$F14,$C$10:$C$18)+SUMIF($F$10:$F$18,"<="&$F14,$D$10:$D$18)+SUMIF('Draw Schedule'!$G$9:$G$17,"<="&$F14,'Draw Schedule'!$E$9:$E$17) -> 40380
A15: 5 | B15: ='Budget & Schedule'!B17 -> Tile & Flooring | C15: =-'Budget & Schedule'!D17*'Your Deal'!$D$33 -> -6525 | D15: =-'Budget & Schedule'!D17*(1-'Your Deal'!$D$33) -> -6525 | E15: ='Draw Schedule'!E14 -> 11745 | F15: ='Budget & Schedule'!G17 -> 46421 | G15: ='Your Deal'!$D$26+SUMIF($F$10:$F$18,"<="&$F15,$C$10:$C$18)+SUMIF($F$10:$F$18,"<="&$F15,$D$10:$D$18)+SUMIF('Draw Schedule'!$G$9:$G$17,"<="&$F15,'Draw Schedule'!$E$9:$E$17) -> 38692.5
A16: 6 | B16: ='Budget & Schedule'!B18 -> Exterior & Landscaping | C16: =-'Budget & Schedule'!D18*'Your Deal'!$D$33 -> -7250 | D16: =-'Budget & Schedule'!D18*(1-'Your Deal'!$D$33) -> -7250 | E16: ='Draw Schedule'!E15 -> 13050 | F16: ='Budget & Schedule'!G18 -> 46443 | G16: ='Your Deal'!$D$26+SUMIF($F$10:$F$18,"<="&$F16,$C$10:$C$18)+SUMIF($F$10:$F$18,"<="&$F16,$D$10:$D$18)+SUMIF('Draw Schedule'!$G$9:$G$17,"<="&$F16,'Draw Schedule'!$E$9:$E$17) -> 35937.5
A17: 7 | B17: ='Budget & Schedule'!B19 -> MEP Finishes, Glass & Appliances | C17: =-'Budget & Schedule'!D19*'Your Deal'!$D$33 -> -6037.5 | D17: =-'Budget & Schedule'!D19*(1-'Your Deal'!$D$33) -> -6037.5 | E17: ='Draw Schedule'!E16 -> 10867.5 | F17: ='Budget & Schedule'!G19 -> 46458 | G17: ='Your Deal'!$D$26+SUMIF($F$10:$F$18,"<="&$F17,$C$10:$C$18)+SUMIF($F$10:$F$18,"<="&$F17,$D$10:$D$18)+SUMIF('Draw Schedule'!$G$9:$G$17,"<="&$F17,'Draw Schedule'!$E$9:$E$17) -> 36912.5
A18: 8 | B18: ='Budget & Schedule'!B20 -> Punch, Carpet & Final Clean | C18: =-'Budget & Schedule'!D20*'Your Deal'!$D$33 -> -3562.5 | D18: =-'Budget & Schedule'!D20*(1-'Your Deal'!$D$33) -> -3562.5 | E18: ='Draw Schedule'!E17 -> 6412.5 | F18: ='Budget & Schedule'!G20 -> 46468 | G18: ='Your Deal'!$D$26+SUMIF($F$10:$F$18,"<="&$F18,$C$10:$C$18)+SUMIF($F$10:$F$18,"<="&$F18,$D$10:$D$18)+SUMIF('Draw Schedule'!$G$9:$G$17,"<="&$F18,'Draw Schedule'!$E$9:$E$17) -> 40655
B20: Lowest your cash ever gets | F20: =MIN(G10:G18) -> 24982.5
B21: Extra cash you need to survive it | F21: =IF($F$20>=0,0,-$F$20) -> 0
A23: This is the number that catches people. A fully funded deal still needs cash on hand between draws.

Sheet Take Into Hona
A1: Take Into Hona
A2: This is your project, ready to build in the app. Phase, category, budget, days.
A6: Rows marked x are your project. Set them up once in Hona and every receipt you scan lands against these numbers.
A8: Ph | B8: Phase | C8: Category | D8: Use? | E8: Budget | F8: Days
A9: ='Scope & Phases'!A8 -> A | B9: ='Scope & Phases'!B8 -> Pre-Construction & General Conditions | C9: ='Scope & Phases'!C8 -> Permits & Plan Review | D9: ='Scope & Phases'!D8 -> x | E9: ='Scope & Phases'!E8 -> 1275 | F9: ='Scope & Phases'!F8 -> 12
A10: ='Scope & Phases'!A9 -> A | B10: ='Scope & Phases'!B9 -> 0 | C10: ='Scope & Phases'!C9 -> Design & Drafting | D10: ='Scope & Phases'!D9 -> 0 | E10: ='Scope & Phases'!E9 -> 0 | F10: ='Scope & Phases'!F9 -> 0
A11: ='Scope & Phases'!A10 -> A | B11: ='Scope & Phases'!B10 -> 0 | C11: ='Scope & Phases'!C10 -> Feasibility & Inspections | D11: ='Scope & Phases'!D10 -> x | E11: ='Scope & Phases'!E10 -> 750 | F11: ='Scope & Phases'!F10 -> 4
A12: ='Scope & Phases'!A11 -> A | B12: ='Scope & Phases'!B11 -> 0 | C12: ='Scope & Phases'!C11 -> Impact & Utility Connection Fees | D12: ='Scope & Phases'!D11 -> 0 | E12: ='Scope & Phases'!E11 -> 0 | F12: ='Scope & Phases'!F11 -> 0
A13: ='Scope & Phases'!A12 -> A | B13: ='Scope & Phases'!B12 -> 0 | C13: ='Scope & Phases'!C12 -> Insurance | D13: ='Scope & Phases'!D12 -> x | E13: ='Scope & Phases'!E12 -> 1675 | F13: ='Scope & Phases'!F12 -> 0
A14: ='Scope & Phases'!A13 -> A | B14: ='Scope & Phases'!B13 -> 0 | C14: ='Scope & Phases'!C13 -> Utility Setup & Deposits | D14: ='Scope & Phases'!D13 -> x | E14: ='Scope & Phases'!E13 -> 400 | F14: ='Scope & Phases'!F13 -> 0
A15: ='Scope & Phases'!A14 -> A | B15: ='Scope & Phases'!B14 -> 0 | C15: ='Scope & Phases'!C14 -> General Conditions & Supervision | D15: ='Scope & Phases'!D14 -> x | E15: ='Scope & Phases'!E14 -> 4225 | F15: ='Scope & Phases'!F14 -> 0
A16: ='Scope & Phases'!A15 -> A | B16: ='Scope & Phases'!B15 -> 0 | C16: ='Scope & Phases'!C15 -> Contingency Reserve | D16: ='Scope & Phases'!D15 -> x | E16: ='Scope & Phases'!E15 -> 6600 | F16: ='Scope & Phases'!F15 -> 0
A17: ='Scope & Phases'!A16 -> 1 | B17: ='Scope & Phases'!B16 -> Demolition, Foundation & Underground | C17: ='Scope & Phases'!C16 -> Mobilization | D17: ='Scope & Phases'!D16 -> x | E17: ='Scope & Phases'!E16 -> 800 | F17: ='Scope & Phases'!F16 -> 2
A18: ='Scope & Phases'!A17 -> 1 | B18: ='Scope & Phases'!B17 -> 0 | C18: ='Scope & Phases'!C17 -> Hazmat Abatement | D18: ='Scope & Phases'!D17 -> 0 | E18: ='Scope & Phases'!E17 -> 0 | F18: ='Scope & Phases'!F17 -> 0
A19: ='Scope & Phases'!A18 -> 1 | B19: ='Scope & Phases'!B18 -> 0 | C19: ='Scope & Phases'!C18 -> Selective Demolition | D19: ='Scope & Phases'!D18 -> x | E19: ='Scope & Phases'!E18 -> 4750 | F19: ='Scope & Phases'!F18 -> 6
A20: ='Scope & Phases'!A19 -> 1 | B20: ='Scope & Phases'!B19 -> 0 | C20: ='Scope & Phases'!C19 -> Excavation & Grading | D20: ='Scope & Phases'!D19 -> 0 | E20: ='Scope & Phases'!E19 -> 0 | F20: ='Scope & Phases'!F19 -> 0
... A74: ='Scope & Phases'!A73 -> 8 | B74: ='Scope & Phases'!B73 -> 0 | C74: ='Scope & Phases'!C73 -> Warranty & Callback Reserve | D74: ='Scope & Phases'!D73 -> x | E74: ='Scope & Phases'!E73 -> 975 | F74: ='Scope & Phases'!F73 -> 0
C75: Project total | E75: =SUMIF(D9:D74,"x",E9:E74) -> 129325
A77: hona · honafinancial.com
